Workbook

Sheet Customers
A1: customer_id | B1: customer_name | C1: segment | D1: join_date | E1: region | F1: status
A2: CUST10000 | B2: Johnson, Olson and Smith | C2: Online | D2: 43918 | E2: North | F2: Active
A3: CUST10001 | B3: Colon-Valdez | C3: Enterprise | D3: 43146 | E3: West | F3: Active
A4: CUST10002 | B4: Henry, Jones and Farley | C4: Online | D4: 44641 | E4: North | F4: Active
A5: CUST10003 | B5: Williams-Dalton | C5: Retail | D5: 44277 | E5: West | F5: Active
A6: CUST10004 | B6: Fisher-Serrano | C6: Enterprise | D6: 43406 | E6: East | F6: Active
A7: CUST10005 | B7: Jennings Ltd | C7: Online | D7: 43663 | E7: South | F7: Active
A8: CUST10006 | B8: Tate-Haas | C8: Retail | D8: 45212 | E8: West | F8: Active
A9: CUST10007 | B9: Brooks, Aguilar and Young | C9: Enterprise | D9: 43234 | E9: North | F9: Active
A10: CUST10008 | B10: Herrera-Ingram | C10: Retail | D10: 43350 | E10: East | F10: Active
A11: CUST10009 | B11: Dunn, Graham and Brown | C11: Retail | D11: 44229 | E11: West | F11: Active
A12: CUST10010 | B12: Moore, Walker and Gutierrez | C12: Retail | D12: 42831 | E12: East | F12: Active
A13: CUST10011 | B13: Turner-Lawson | C13: Enterprise | D13: 42920 | E13: West | F13: Active
... A401: CUST10399 | B401: Marshall-Horne | C401: Enterprise | D401: 43563 | E401: East | F401: Inactive

Sheet Vendors
A1: vendor_id | B1: vendor_name | C1: category | D1: region | E1: active
A2: VEND1000 | B2: Johnson-Howard | C2: Supplies | D2: East | E2: Y
A3: VEND1001 | B3: Jensen Ltd | C3: Consulting | D3: South | E3: Y
A4: VEND1002 | B4: Collins Group | C4: Services | D4: North | E4: Y
A5: VEND1003 | B5: Smith, Kirby and Torres | C5: Utilities | D5: North | E5: Y
A6: VEND1004 | B6: Mcgrath, Wheeler and Boyd | C6: Utilities | D6: North | E6: Y
A7: VEND1005 | B7: Cooper-Larson | C7: Supplies | D7: South | E7: Y
A8: VEND1006 | B8: Ward-David | C8: Utilities | D8: South | E8: Y
A9: VEND1007 | B9: Savage Ltd | C9: Utilities | D9: West | E9: Y
A10: VEND1008 | B10: Medina-Lee | C10: Services | D10: South | E10: Y
A11: VEND1009 | B11: Griffith and Sons | C11: Services | D11: East | E11: Y
A12: VEND1010 | B12: Thomas-Santana | C12: Rent | D12: South | E12: Y
... A121: VEND1119 | B121: Graham-Lopez | C121: Consulting | D121: North | E121: N

Sheet Headcount
A1: employee_id | B1: employee_name | C1: business_unit | D1: join_date | E1: status | F1: region | G1: cost_to_company
A2: EMP1000 | B2: Daniel Thornton | C2: Enterprise | D2: 44968 | E2: Active | F2: South | G2: 1566441
A3: EMP1001 | B3: Ashley Burch | C3: Retail | D3: 44084 | E3: Active | F3: West | G3: 1533942
A4: EMP1002 | B4: Angel Perry | C4: Online | D4: 44620 | E4: Active | F4: East | G4: 962333
A5: EMP1003 | B5: Kimberly Harmon | C5: Online | D5: 44484 | E5: Active | F5: North | G5: 503403
A6: EMP1004 | B6: Sarah Smith DDS | C6: Enterprise | D6: 44957 | E6: Active | F6: West | G6: 1051271
A7: EMP1005 | B7: Sierra Jordan | C7: Enterprise | D7: 44945 | E7: Active | F7: South | G7: 731473
A8: EMP1006 | B8: Adam Wood | C8: Enterprise | D8: 43768 | E8: Active | F8: West | G8: 596883
A9: EMP1007 | B9: Keith Collins | C9: Online | D9: 44993 | E9: Active | F9: East | G9: 864597
A10: EMP1008 | B10: Mitchell Kelly | C10: Enterprise | D10: 44438 | E10: Active | F10: North | G10: 1736454
A11: EMP1009 | B11: Jacob Mendez | C11: Enterprise | D11: 45166 | E11: Active | F11: North | G11: 1479884
A12: EMP1010 | B12: William Bryant | C12: Enterprise | D12: 44563 | E12: Active | F12: North | G12: 1160373
A13: EMP1011 | B13: Sean Daniels | C13: Retail | D13: 44741 | E13: Active | F13: South | G13: 1603487
... A201: EMP1199 | B201: Mr. Alec Nelson | C201: Enterprise | D201: 44808 | E201: Inactive | F201: South | G201: 728593

Sheet Budget
A1: year | B1: month | C1: business_unit | D1: budgeted_revenue | E1: budgeted_expense
A2: 2022 | B2: 1 | C2: Retail | D2: 1530660 | E2: 1259760
A3: 2022 | B3: 1 | C3: Enterprise | D3: 1689240 | E3: 1152615
A4: 2022 | B4: 1 | C4: Online | D4: 2069088 | E4: 1776169
A5: 2022 | B5: 2 | C5: Retail | D5: 1836984 | E5: 1201730
A6: 2022 | B6: 2 | C6: Enterprise | D6: 1923012 | E6: 1454263
A7: 2022 | B7: 2 | C7: Online | D7: 1516272 | E7: 1117069
A8: 2022 | B8: 3 | C8: Retail | D8: 1510920 | E8: 1106833
A9: 2022 | B9: 3 | C9: Enterprise | D9: 1576692 | E9: 959653
A10: 2022 | B10: 3 | C10: Online | D10: 2119464 | E10: 1677676
A11: 2022 | B11: 4 | C11: Retail | D11: 1731204 | E11: 1275919
A12: 2022 | B12: 4 | C12: Enterprise | D12: 2042184 | E12: 1592655
A13: 2022 | B13: 4 | C13: Online | D13: 2132844 | E13: 1388082
... A73: 2023 | B73: 12 | C73: Online | D73: 2263008 | E73: 1662605

Sheet Financial_Transactions
A1: transaction_id | B1: transaction_date | C1: amount | D1: account_type | E1: category | F1: business_unit | G1: region | H1: customer_id | I1: vendor_id | J1: description | K1: customer_fk_check | L1: vendor_fk_check | M1: headcount_fk_check
A2: TRX100000 | B2: 45172 | C2: -66631.73 | D2: Expense | E2: Supplies | F2: Online | G2: West | I2: VEND1053 | J2: Begin catch control dark practice. | K2: =IF(ISNA(XLOOKUP(A2,Customers!A:A,Customers!A:A)),"Invalid FK","Valid") -> Valid | L2: =IF(ISNA(XLOOKUP(B2,Vendors!A:A,Vendors!A:A)),"Invalid FK","Valid") -> Valid | M2: =IF(ISNA(XLOOKUP(C2,Headcount!C:C,Headcount!C:C)),"Invalid FK","Valid") -> Valid
A3: TRX100001 | B3: 45182 | C3: -54305.58 | D3: Expense | E3: Utilities | F3: Enterprise | G3: East | I3: VEND1059 | J3: Style guy soldier boy energy above. | K3: =IF(ISNA(XLOOKUP(A3,Customers!A:A,Customers!A:A)),"Invalid FK","Valid") -> Valid | L3: =IF(ISNA(XLOOKUP(B3,Vendors!A:A,Vendors!A:A)),"Invalid FK","Valid") -> Valid | M3: =IF(ISNA(XLOOKUP(C3,Headcount!C:C,Headcount!C:C)),"Invalid FK","Valid") -> Valid
A4: TRX100002 | B4: 45104 | C4: 146074.92 | D4: Revenue | E4: Subscription | F4: Online | G4: East | H4: CUST10122 | J4: Skill surface drug personal western. | K4: =IF(ISNA(XLOOKUP(A4,Customers!A:A,Customers!A:A)),"Invalid FK","Valid") -> Valid | L4: =IF(ISNA(XLOOKUP(B4,Vendors!A:A,Vendors!A:A)),"Invalid FK","Valid") -> Valid | M4: =IF(ISNA(XLOOKUP(C4,Headcount!C:C,Headcount!C:C)),"Invalid FK","Valid") -> Valid
A5: TRX100003 | B5: 45102 | C5: 212157.95 | D5: Revenue | E5: Service | F5: Enterprise | G5: West | H5: CUST10027 | J5: Develop many it I rich floor decide. | K5: =IF(ISNA(XLOOKUP(A5,Customers!A:A,Customers!A:A)),"Invalid FK","Valid") -> Valid | L5: =IF(ISNA(XLOOKUP(B5,Vendors!A:A,Vendors!A:A)),"Invalid FK","Valid") -> Valid | M5: =IF(ISNA(XLOOKUP(C5,Headcount!C:C,Headcount!C:C)),"Invalid FK","Valid") -> Valid
A6: TRX100004 | B6: 45245 | C6: -35944.73 | D6: Expense | E6: Rent | F6: Enterprise | G6: North | I6: VEND1046 | J6: Choose thought teach never. | K6: =IF(ISNA(XLOOKUP(A6,Customers!A:A,Customers!A:A)),"Invalid FK","Valid") -> Valid | L6: =IF(ISNA(XLOOKUP(B6,Vendors!A:A,Vendors!A:A)),"Invalid FK","Valid") -> Valid | M6: =IF(ISNA(XLOOKUP(C6,Headcount!C:C,Headcount!C:C)),"Invalid FK","Valid") -> Valid
A7: TRX100005 | B7: 44989 | C7: 90953.83 | D7: Revenue | E7: Service | F7: Retail | G7: South | H7: CUST10332 | J7: Dinner present unit lay course. | K7: =IF(ISNA(XLOOKUP(A7,Customers!A:A,Customers!A:A)),"Invalid FK","Valid") -> Valid | L7: =IF(ISNA(XLOOKUP(B7,Vendors!A:A,Vendors!A:A)),"Invalid FK","Valid") -> Valid | M7: =IF(ISNA(XLOOKUP(C7,Headcount!C:C,Headcount!C:C)),"Invalid FK","Valid") -> Valid
A8: TRX100006 | B8: 45115 | C8: 73251.21 | D8: Revenue | E8: Service | F8: Online | G8: West | H8: CUST10270 | J8: Data ago arm care hundred represent wonder. | K8: =IF(ISNA(XLOOKUP(A8,Customers!A:A,Customers!A:A)),"Invalid FK","Valid") -> Valid | L8: =IF(ISNA(XLOOKUP(B8,Vendors!A:A,Vendors!A:A)),"Invalid FK","Valid") -> Valid | M8: =IF(ISNA(XLOOKUP(C8,Headcount!C:C,Headcount!C:C)),"Invalid FK","Valid") -> Valid
A9: TRX100007 | B9: 44644 | C9: -21064.02 | D9: Expense | E9: Marketing | F9: Online | G9: East | I9: VEND1115 | J9: Sign such remember range ability. | K9: =IF(ISNA(XLOOKUP(A9,Customers!A:A,Customers!A:A)),"Invalid FK","Valid") -> Valid | L9: =IF(ISNA(XLOOKUP(B9,Vendors!A:A,Vendors!A:A)),"Invalid FK","Valid") -> Valid | M9: =IF(ISNA(XLOOKUP(C9,Headcount!C:C,Headcount!C:C)),"Invalid FK","Valid") -> Valid
A10: TRX100008 | B10: 44775 | C10: 136347.73 | D10: Revenue | E10: Product | F10: Retail | G10: West | H10: CUST10168 | J10: Poor similar feeling close require probably rather thought. | K10: =IF(ISNA(XLOOKUP(A10,Customers!A:A,Customers!A:A)),"Invalid FK","Valid") -> Valid | L10: =IF(ISNA(XLOOKUP(B10,Vendors!A:A,Vendors!A:A)),"Invalid FK","Valid") -> Valid | M10: =IF(ISNA(XLOOKUP(C10,Headcount!C:C,Headcount!C:C)),"Invalid FK","Valid") -> Valid
A11: TRX100009 | B11: 45094 | C11: 159482 | D11: Revenue | E11: Product | F11: Retail | G11: West | H11: CUST10151 | J11: Cause worker statement office able foot. | K11: =IF(ISNA(XLOOKUP(A11,Customers!A:A,Customers!A:A)),"Invalid FK","Valid") -> Valid | L11: =IF(ISNA(XLOOKUP(B11,Vendors!A:A,Vendors!A:A)),"Invalid FK","Valid") -> Valid | M11: =IF(ISNA(XLOOKUP(C11,Headcount!C:C,Headcount!C:C)),"Invalid FK","Valid") -> Valid
A12: TRX100010 | B12: 44749 | C12: 15882.36 | D12: Equity | E12: Equity | F12: Retail | G12: South | J12: Ready enter quite attack resource list commercial. | K12: =IF(ISNA(XLOOKUP(A12,Customers!A:A,Customers!A:A)),"Invalid FK","Valid") -> Valid | L12: =IF(ISNA(XLOOKUP(B12,Vendors!A:A,Vendors!A:A)),"Invalid FK","Valid") -> Valid | M12: =IF(ISNA(XLOOKUP(C12,Headcount!C:C,Headcount!C:C)),"Invalid FK","Valid") -> Valid
A13: TRX100011 | B13: 44781 | C13: 217487.82 | D13: Revenue | E13: Product | F13: Online | G13: North | H13: CUST10353 | J13: Before green media feeling Mr half trouble. | K13: =IF(ISNA(XLOOKUP(A13,Customers!A:A,Customers!A:A)),"Invalid FK","Valid") -> Valid | L13: =IF(ISNA(XLOOKUP(B13,Vendors!A:A,Vendors!A:A)),"Invalid FK","Valid") -> Valid | M13: =IF(ISNA(XLOOKUP(C13,Headcount!C:C,Headcount!C:C)),"Invalid FK","Valid") -> Valid
A14: TRX100012 | B14: 45001 | C14: -8913.27 | D14: Expense | E14: Other | F14: Enterprise | G14: East | I14: VEND1067 | J14: Rise discover visit security end buy medical think. | K14: =IF(ISNA(XLOOKUP(A14,Customers!A:A,Customers!A:A)),"Invalid FK","Valid") -> Valid | L14: =IF(ISNA(XLOOKUP(B14,Vendors!A:A,Vendors!A:A)),"Invalid FK","Valid") -> Valid | M14: =IF(ISNA(XLOOKUP(C14,Headcount!C:C,Headcount!C:C)),"Invalid FK","Valid") -> Valid
A15: TRX100013 | B15: 45270 | C15: 139523.96 | D15: Revenue | E15: Service | F15: Retail | G15: North | H15: CUST10243 | J15: Military line exist little education family world. | K15: =IF(ISNA(XLOOKUP(A15,Customers!A:A,Customers!A:A)),"Invalid FK","Valid") -> Valid | L15: =IF(ISNA(XLOOKUP(B15,Vendors!A:A,Vendors!A:A)),"Invalid FK","Valid") -> Valid | M15: =IF(ISNA(XLOOKUP(C15,Headcount!C:C,Headcount!C:C)),"Invalid FK","Valid") -> Valid
A16: TRX100014 | B16: 45125 | C16: 165589.04 | D16: Revenue | E16: Service | F16: Online | G16: East | H16: CUST10357 | J16: Artist place loss morning. | K16: =IF(ISNA(XLOOKUP(A16,Customers!A:A,Customers!A:A)),"Invalid FK","Valid") -> Valid | L16: =IF(ISNA(XLOOKUP(B16,Vendors!A:A,Vendors!A:A)),"Invalid FK","Valid") -> Valid | M16: =IF(ISNA(XLOOKUP(C16,Headcount!C:C,Headcount!C:C)),"Invalid FK","Valid") -> Valid
A17: TRX100015 | B17: 44952 | C17: 262541.15 | D17: Revenue | E17: Service | F17: Retail | G17: West | H17: CUST10045 | J17: Game evidence support skill pretty. | K17: =IF(ISNA(XLOOKUP(A17,Customers!A:A,Customers!A:A)),"Invalid FK","Valid") -> Valid | L17: =IF(ISNA(XLOOKUP(B17,Vendors!A:A,Vendors!A:A)),"Invalid FK","Valid") -> Valid | M17: =IF(ISNA(XLOOKUP(C17,Headcount!C:C,Headcount!C:C)),"Invalid FK","Valid") -> Valid
A18: TRX100016 | B18: 45087 | C18: 152113.39 | D18: Revenue | E18: Service | F18: Online | G18: South | H18: CUST10120 | J18: Bad author generation decade increase. | K18: =IF(ISNA(XLOOKUP(A18,Customers!A:A,Customers!A:A)),"Invalid FK","Valid") -> Valid | L18: =IF(ISNA(XLOOKUP(B18,Vendors!A:A,Vendors!A:A)),"Invalid FK","Valid") -> Valid | M18: =IF(ISNA(XLOOKUP(C18,Headcount!C:C,Headcount!C:C)),"Invalid FK","Valid") -> Valid
A19: TRX100017 | B19: 44726 | C19: 107495.7 | D19: Revenue | E19: Service | F19: Online | G19: North | H19: CUST10228 | J19: Left own eat wife tell with. | K19: =IF(ISNA(XLOOKUP(A19,Customers!A:A,Customers!A:A)),"Invalid FK","Valid") -> Valid | L19: =IF(ISNA(XLOOKUP(B19,Vendors!A:A,Vendors!A:A)),"Invalid FK","Valid") -> Valid | M19: =IF(ISNA(XLOOKUP(C19,Headcount!C:C,Headcount!C:C)),"Invalid FK","Valid") -> Valid
A20: TRX100018 | B20: 45190 | C20: 83127.62 | D20: Revenue | E20: Subscription | F20: Online | G20: West | H20: CUST10333 | J20: Individual first region. | K20: =IF(ISNA(XLOOKUP(A20,Customers!A:A,Customers!A:A)),"Invalid FK","Valid") -> Valid | L20: =IF(ISNA(XLOOKUP(B20,Vendors!A:A,Vendors!A:A)),"Invalid FK","Valid") -> Valid | M20: =IF(ISNA(XLOOKUP(C20,Headcount!C:C,Headcount!C:C)),"Invalid FK","Valid") -> Valid
A21: TRX100019 | B21: 44793 | C21: 145634.47 | D21: Revenue | E21: Service | F21: Enterprise | G21: West | H21: CUST10302 | J21: Rise war shake doctor. | K21: =IF(ISNA(XLOOKUP(A21,Customers!A:A,Customers!A:A)),"Invalid FK","Valid") -> Valid | L21: =IF(ISNA(XLOOKUP(B21,Vendors!A:A,Vendors!A:A)),"Invalid FK","Valid") -> Valid | M21: =IF(ISNA(XLOOKUP(C21,Headcount!C:C,Headcount!C:C)),"Invalid FK","Valid") -> Valid
A22: TRX100020 | B22: 45062 | C22: 167566.97 | D22: Revenue | E22: Service | F22: Retail | G22: North | H22: CUST10042 | J22: Before expect allow job one set. | K22: =IF(ISNA(XLOOKUP(A22,Customers!A:A,Customers!A:A)),"Invalid FK","Valid") -> Valid | L22: =IF(ISNA(XLOOKUP(B22,Vendors!A:A,Vendors!A:A)),"Invalid FK","Valid") -> Valid | M22: =IF(ISNA(XLOOKUP(C22,Headcount!C:C,Headcount!C:C)),"Invalid FK","Valid") -> Valid
A23: TRX100021 | B23: 44726 | C23: -2000 | D23: Expense | E23: Rent | F23: Online | G23: West | I23: VEND1022 | J23: Side official leave seem financial. | K23: =IF(ISNA(XLOOKUP(A23,Customers!A:A,Customers!A:A)),"Invalid FK","Valid") -> Valid | L23: =IF(ISNA(XLOOKUP(B23,Vendors!A:A,Vendors!A:A)),"Invalid FK","Valid") -> Valid | M23: =IF(ISNA(XLOOKUP(C23,Headcount!C:C,Headcount!C:C)),"Invalid FK","Valid") -> Valid
A24: TRX100022 | B24: 44998 | C24: 203374.65 | D24: Revenue | E24: Service | F24: Online | G24: South | H24: CUST10021 | J24: Must require bit relate Congress local improve organization. | K24: =IF(ISNA(XLOOKUP(A24,Customers!A:A,Customers!A:A)),"Invalid FK","Valid") -> Valid | L24: =IF(ISNA(XLOOKUP(B24,Vendors!A:A,Vendors!A:A)),"Invalid FK","Valid") -> Valid | M24: =IF(ISNA(XLOOKUP(C24,Headcount!C:C,Headcount!C:C)),"Invalid FK","Valid") -> Valid
A25: TRX100023 | B25: 45189 | C25: 171433.19 | D25: Revenue | E25: Product | F25: Enterprise | G25: West | H25: CUST10218 | J25: Identify loss across fact government sea upon. | K25: =IF(ISNA(XLOOKUP(A25,Customers!A:A,Customers!A:A)),"Invalid FK","Valid") -> Valid | L25: =IF(ISNA(XLOOKUP(B25,Vendors!A:A,Vendors!A:A)),"Invalid FK","Valid") -> Valid | M25: =IF(ISNA(XLOOKUP(C25,Headcount!C:C,Headcount!C:C)),"Invalid FK","Valid") -> Valid
A26: TRX100024 | B26: 44850 | C26: -60198.87 | D26: Expense | E26: Payroll | F26: Enterprise | G26: North | I26: VEND1058 | J26: Big fine cause full reality heart condition another. | K26: =IF(ISNA(XLOOKUP(A26,Customers!A:A,Customers!A:A)),"Invalid FK","Valid") -> Valid | L26: =IF(ISNA(XLOOKUP(B26,Vendors!A:A,Vendors!A:A)),"Invalid FK","Valid") -> Valid | M26: =IF(ISNA(XLOOKUP(C26,Headcount!C:C,Headcount!C:C)),"Invalid FK","Valid") -> Valid
A27: TRX100025 | B27: 45097 | C27: -40143.88 | D27: Expense | E27: Rent | F27: Retail | G27: West | I27: VEND1037 | J27: Good owner financial any result summer physical. | K27: =IF(ISNA(XLOOKUP(A27,Customers!A:A,Customers!A:A)),"Invalid FK","Valid") -> Valid | L27: =IF(ISNA(XLOOKUP(B27,Vendors!A:A,Vendors!A:A)),"Invalid FK","Valid") -> Valid | M27: =IF(ISNA(XLOOKUP(C27,Headcount!C:C,Headcount!C:C)),"Invalid FK","Valid") -> Valid
A28: TRX100026 | B28: 45208 | C28: -38329 | D28: Expense | E28: Marketing | F28: Enterprise | G28: West | I28: VEND1049 | J28: Sport note decide who modern car knowledge. | K28: =IF(ISNA(XLOOKUP(A28,Customers!A:A,Customers!A:A)),"Invalid FK","Valid") -> Valid | L28: =IF(ISNA(XLOOKUP(B28,Vendors!A:A,Vendors!A:A)),"Invalid FK","Valid") -> Valid | M28: =IF(ISNA(XLOOKUP(C28,Headcount!C:C,Headcount!C:C)),"Invalid FK","Valid") -> Valid
A29: TRX100027 | B29: 44901 | C29: 193475.45 | D29: Revenue | E29: Service | F29: Retail | G29: South | H29: CUST10146 | J29: Game step assume late home order morning to. | K29: =IF(ISNA(XLOOKUP(A29,Customers!A:A,Customers!A:A)),"Invalid FK","Valid") -> Valid | L29: =IF(ISNA(XLOOKUP(B29,Vendors!A:A,Vendors!A:A)),"Invalid FK","Valid") -> Valid | M29: =IF(ISNA(XLOOKUP(C29,Headcount!C:C,Headcount!C:C)),"Invalid FK","Valid") -> Valid
A30: TRX100028 | B30: 45002 | C30: 139672.98 | D30: Revenue | E30: Subscription | F30: Enterprise | G30: South | H30: CUST10074 | J30: Nature need environment operation country easy across choice. | K30: =IF(ISNA(XLOOKUP(A30,Customers!A:A,Customers!A:A)),"Invalid FK","Valid") -> Valid | L30: =IF(ISNA(XLOOKUP(B30,Vendors!A:A,Vendors!A:A)),"Invalid FK","Valid") -> Valid | M30: =IF(ISNA(XLOOKUP(C30,Headcount!C:C,Headcount!C:C)),"Invalid FK","Valid") -> Valid
A31: TRX100029 | B31: 45188 | C31: 198385.78 | D31: Revenue | E31: Subscription | F31: Enterprise | G31: North | H31: CUST10011 | J31: Scientist particularly include true listen happy. | K31: =IF(ISNA(XLOOKUP(A31,Customers!A:A,Customers!A:A)),"Invalid FK","Valid") -> Valid | L31: =IF(ISNA(XLOOKUP(B31,Vendors!A:A,Vendors!A:A)),"Invalid FK","Valid") -> Valid | M31: =IF(ISNA(XLOOKUP(C31,Headcount!C:C,Headcount!C:C)),"Invalid FK","Valid") -> Valid
A32: TRX100030 | B32: 44814 | C32: 137108.16 | D32: Revenue | E32: Service | F32: Enterprise | G32: East | H32: CUST10325 | J32: Citizen help never simple course. | K32: =IF(ISNA(XLOOKUP(A32,Customers!A:A,Customers!A:A)),"Invalid FK","Valid") -> Valid | L32: =IF(ISNA(XLOOKUP(B32,Vendors!A:A,Vendors!A:A)),"Invalid FK","Valid") -> Valid | M32: =IF(ISNA(XLOOKUP(C32,Headcount!C:C,Headcount!C:C)),"Invalid FK","Valid") -> Valid
A33: TRX100031 | B33: 44624 | C33: -44326.21 | D33: Expense | E33: Other | F33: Retail | G33: East | I33: VEND1053 | J33: Billion newspaper modern fine career somebody. | K33: =IF(ISNA(XLOOKUP(A33,Customers!A:A,Customers!A:A)),"Invalid FK","Valid") -> Valid | L33: =IF(ISNA(XLOOKUP(B33,Vendors!A:A,Vendors!A:A)),"Invalid FK","Valid") -> Valid | M33: =IF(ISNA(XLOOKUP(C33,Headcount!C:C,Headcount!C:C)),"Invalid FK","Valid") -> Valid
A34: TRX100032 | B34: 44970 | C34: 162088.99 | D34: Revenue | E34: Service | F34: Enterprise | G34: North | H34: CUST10203 | J34: Wall campaign might anyone. | K34: =IF(ISNA(XLOOKUP(A34,Customers!A:A,Customers!A:A)),"Invalid FK","Valid") -> Valid | L34: =IF(ISNA(XLOOKUP(B34,Vendors!A:A,Vendors!A:A)),"Invalid FK","Valid") -> Valid | M34: =IF(ISNA(XLOOKUP(C34,Headcount!C:C,Headcount!C:C)),"Invalid FK","Valid") -> Valid
A35: TRX100033 | B35: 44847 | C35: 138103.68 | D35: Revenue | E35: Subscription | F35: Online | G35: North | H35: CUST10151 | J35: Could impact decide key. | K35: =IF(ISNA(XLOOKUP(A35,Customers!A:A,Customers!A:A)),"Invalid FK","Valid") -> Valid | L35: =IF(ISNA(XLOOKUP(B35,Vendors!A:A,Vendors!A:A)),"Invalid FK","Valid") -> Valid | M35: =IF(ISNA(XLOOKUP(C35,Headcount!C:C,Headcount!C:C)),"Invalid FK","Valid") -> Valid
A36: TRX100034 | B36: 44695 | C36: -10197.61 | D36: Expense | E36: Utilities | F36: Retail | G36: East | I36: VEND1014 | J36: Imagine must who discover since painting. | K36: =IF(ISNA(XLOOKUP(A36,Customers!A:A,Customers!A:A)),"Invalid FK","Valid") -> Valid | L36: =IF(ISNA(XLOOKUP(B36,Vendors!A:A,Vendors!A:A)),"Invalid FK","Valid") -> Valid | M36: =IF(ISNA(XLOOKUP(C36,Headcount!C:C,Headcount!C:C)),"Invalid FK","Valid") -> Valid
A37: TRX100035 | B37: 45145 | C37: -62926.94 | D37: Expense | E37: Marketing | F37: Retail | G37: West | I37: VEND1093 | J37: Training nor arrive. | K37: =IF(ISNA(XLOOKUP(A37,Customers!A:A,Customers!A:A)),"Invalid FK","Valid") -> Valid | L37: =IF(ISNA(XLOOKUP(B37,Vendors!A:A,Vendors!A:A)),"Invalid FK","Valid") -> Valid | M37: =IF(ISNA(XLOOKUP(C37,Headcount!C:C,Headcount!C:C)),"Invalid FK","Valid") -> Valid
A38: TRX100036 | B38: 45195 | C38: 144593.87 | D38: Revenue | E38: Service | F38: Enterprise | G38: East | H38: CUST10086 | J38: Field some arrive society everybody guy public. | K38: =IF(ISNA(XLOOKUP(A38,Customers!A:A,Customers!A:A)),"Invalid FK","Valid") -> Valid | L38: =IF(ISNA(XLOOKUP(B38,Vendors!A:A,Vendors!A:A)),"Invalid FK","Valid") -> Valid | M38: =IF(ISNA(XLOOKUP(C38,Headcount!C:C,Headcount!C:C)),"Invalid FK","Valid") -> Valid
A39: TRX100037 | B39: 44595 | C39: 38814.58 | D39: Revenue | E39: Product | F39: Retail | G39: North | H39: CUST10013 | J39: Order agreement mind everything. | K39: =IF(ISNA(XLOOKUP(A39,Customers!A:A,Customers!A:A)),"Invalid FK","Valid") -> Valid | L39: =IF(ISNA(XLOOKUP(B39,Vendors!A:A,Vendors!A:A)),"Invalid FK","Valid") -> Valid | M39: =IF(ISNA(XLOOKUP(C39,Headcount!C:C,Headcount!C:C)),"Invalid FK","Valid") -> Valid
A40: TRX100038 | B40: 44983 | C40: -36977.97 | D40: Expense | E40: Rent | F40: Online | G40: East | I40: VEND1082 | J40: Watch would miss interview water trouble. | K40: =IF(ISNA(XLOOKUP(A40,Customers!A:A,Customers!A:A)),"Invalid FK","Valid") -> Valid | L40: =IF(ISNA(XLOOKUP(B40,Vendors!A:A,Vendors!A:A)),"Invalid FK","Valid") -> Valid | M40: =IF(ISNA(XLOOKUP(C40,Headcount!C:C,Headcount!C:C)),"Invalid FK","Valid") -> Valid
A41: TRX100039 | B41: 44914 | C41: -18304.84 | D41: Expense | E41: Payroll | F41: Enterprise | G41: East | I41: VEND1106 | J41: Save in thing model. | K41: =IF(ISNA(XLOOKUP(A41,Customers!A:A,Customers!A:A)),"Invalid FK","Valid") -> Valid | L41: =IF(ISNA(XLOOKUP(B41,Vendors!A:A,Vendors!A:A)),"Invalid FK","Valid") -> Valid | M41: =IF(ISNA(XLOOKUP(C41,Headcount!C:C,Headcount!C:C)),"Invalid FK","Valid") -> Valid
A42: TRX100040 | B42: 45228 | C42: 248459.88 | D42: Revenue | E42: Subscription | F42: Online | G42: East | H42: CUST10022 | J42: Defense argue help someone action throw. | K42: =IF(ISNA(XLOOKUP(A42,Customers!A:A,Customers!A:A)),"Invalid FK","Valid") -> Valid | L42: =IF(ISNA(XLOOKUP(B42,Vendors!A:A,Vendors!A:A)),"Invalid FK","Valid") -> Valid | M42: =IF(ISNA(XLOOKUP(C42,Headcount!C:C,Headcount!C:C)),"Invalid FK","Valid") -> Valid
A43: TRX100041 | B43: 44838 | C43: 120099.72 | D43: Revenue | E43: Product | F43: Online | G43: East | H43: CUST10128 | J43: Reduce suddenly against ball medical. | K43: =IF(ISNA(XLOOKUP(A43,Customers!A:A,Customers!A:A)),"Invalid FK","Valid") -> Valid | L43: =IF(ISNA(XLOOKUP(B43,Vendors!A:A,Vendors!A:A)),"Invalid FK","Valid") -> Valid | M43: =IF(ISNA(XLOOKUP(C43,Headcount!C:C,Headcount!C:C)),"Invalid FK","Valid") -> Valid
A44: TRX100042 | B44: 44888 | C44: -39571.02 | D44: Expense | E44: Other | F44: Online | G44: South | I44: VEND1063 | J44: Far make skill lose audience art. | K44: =IF(ISNA(XLOOKUP(A44,Customers!A:A,Customers!A:A)),"Invalid FK","Valid") -> Valid | L44: =IF(ISNA(XLOOKUP(B44,Vendors!A:A,Vendors!A:A)),"Invalid FK","Valid") -> Valid | M44: =IF(ISNA(XLOOKUP(C44,Headcount!C:C,Headcount!C:C)),"Invalid FK","Valid") -> Valid
A45: TRX100043 | B45: 45033 | C45: 79909.54 | D45: Revenue | E45: Subscription | F45: Retail | G45: East | H45: CUST10251 | J45: Tax north line it fund describe. | K45: =IF(ISNA(XLOOKUP(A45,Customers!A:A,Customers!A:A)),"Invalid FK","Valid") -> Valid | L45: =IF(ISNA(XLOOKUP(B45,Vendors!A:A,Vendors!A:A)),"Invalid FK","Valid") -> Valid | M45: =IF(ISNA(XLOOKUP(C45,Headcount!C:C,Headcount!C:C)),"Invalid FK","Valid") -> Valid
A46: TRX100044 | B46: 44977 | C46: -50444.36 | D46: Expense | E46: Other | F46: Enterprise | G46: North | I46: VEND1020 | J46: Follow put campaign lose summer lot if others. | K46: =IF(ISNA(XLOOKUP(A46,Customers!A:A,Customers!A:A)),"Invalid FK","Valid") -> Valid | L46: =IF(ISNA(XLOOKUP(B46,Vendors!A:A,Vendors!A:A)),"Invalid FK","Valid") -> Valid | M46: =IF(ISNA(XLOOKUP(C46,Headcount!C:C,Headcount!C:C)),"Invalid FK","Valid") -> Valid
A47: TRX100045 | B47: 44879 | C47: -22716.39 | D47: Expense | E47: Supplies | F47: Retail | G47: East | I47: VEND1062 | J47: Structure have effect. | K47: =IF(ISNA(XLOOKUP(A47,Customers!A:A,Customers!A:A)),"Invalid FK","Valid") -> Valid | L47: =IF(ISNA(XLOOKUP(B47,Vendors!A:A,Vendors!A:A)),"Invalid FK","Valid") -> Valid | M47: =IF(ISNA(XLOOKUP(C47,Headcount!C:C,Headcount!C:C)),"Invalid FK","Valid") -> Valid
A48: TRX100046 | B48: 44934 | C48: -14936.32 | D48: Expense | E48: Marketing | F48: Online | G48: East | I48: VEND1025 | J48: Second get its since return. | K48: =IF(ISNA(XLOOKUP(A48,Customers!A:A,Customers!A:A)),"Invalid FK","Valid") -> Valid | L48: =IF(ISNA(XLOOKUP(B48,Vendors!A:A,Vendors!A:A)),"Invalid FK","Valid") -> Valid | M48: =IF(ISNA(XLOOKUP(C48,Headcount!C:C,Headcount!C:C)),"Invalid FK","Valid") -> Valid
A49: TRX100047 | B49: 45199 | C49: 141946.92 | D49: Revenue | E49: Service | F49: Retail | G49: West | H49: CUST10342 | J49: Then section each support majority. | K49: =IF(ISNA(XLOOKUP(A49,Customers!A:A,Customers!A:A)),"Invalid FK","Valid") -> Valid | L49: =IF(ISNA(XLOOKUP(B49,Vendors!A:A,Vendors!A:A)),"Invalid FK","Valid") -> Valid | M49: =IF(ISNA(XLOOKUP(C49,Headcount!C:C,Headcount!C:C)),"Invalid FK","Valid") -> Valid
A50: TRX100048 | B50: 45265 | C50: -28844.76 | D50: Expense | E50: Supplies | F50: Online | G50: West | I50: VEND1060 | J50: Where keep leader computer father brother a give. | K50: =IF(ISNA(XLOOKUP(A50,Customers!A:A,Customers!A:A)),"Invalid FK","Valid") -> Valid | L50: =IF(ISNA(XLOOKUP(B50,Vendors!A:A,Vendors!A:A)),"Invalid FK","Valid") -> Valid | M50: =IF(ISNA(XLOOKUP(C50,Headcount!C:C,Headcount!C:C)),"Invalid FK","Valid") -> Valid
A51: TRX100049 | B51: 44782 | C51: -66244 | D51: Expense | E51: Supplies | F51: Enterprise | G51: North | I51: VEND1089 | J51: Big itself serious. | K51: =IF(ISNA(XLOOKUP(A51,Customers!A:A,Customers!A:A)),"Invalid FK","Valid") -> Valid | L51: =IF(ISNA(XLOOKUP(B51,Vendors!A:A,Vendors!A:A)),"Invalid FK","Valid") -> Valid | M51: =IF(ISNA(XLOOKUP(C51,Headcount!C:C,Headcount!C:C)),"Invalid FK","Valid") -> Valid
A52: TRX100050 | B52: 45018 | C52: 15704.88 | D52: Asset | E52: Asset | F52: Enterprise | G52: East | J52: Test fill perform voice. | K52: =IF(ISNA(XLOOKUP(A52,Customers!A:A,Customers!A:A)),"Invalid FK","Valid") -> Valid | L52: =IF(ISNA(XLOOKUP(B52,Vendors!A:A,Vendors!A:A)),"Invalid FK","Valid") -> Valid | M52: =IF(ISNA(XLOOKUP(C52,Headcount!C:C,Headcount!C:C)),"Invalid FK","Valid") -> Valid
A53: TRX100051 | B53: 44822 | C53: 209846.71 | D53: Revenue | E53: Subscription | F53: Retail | G53: South | H53: CUST10190 | J53: School common voice itself. | K53: =IF(ISNA(XLOOKUP(A53,Customers!A:A,Customers!A:A)),"Invalid FK","Valid") -> Valid | L53: =IF(ISNA(XLOOKUP(B53,Vendors!A:A,Vendors!A:A)),"Invalid FK","Valid") -> Valid | M53: =IF(ISNA(XLOOKUP(C53,Headcount!C:C,Headcount!C:C)),"Invalid FK","Valid") -> Valid
A54: TRX100052 | B54: 44728 | C54: -45798.81 | D54: Expense | E54: Marketing | F54: Enterprise | G54: East | I54: VEND1011 | J54: Majority early special record sit scene price. | K54: =IF(ISNA(XLOOKUP(A54,Customers!A:A,Customers!A:A)),"Invalid FK","Valid") -> Valid | L54: =IF(ISNA(XLOOKUP(B54,Vendors!A:A,Vendors!A:A)),"Invalid FK","Valid") -> Valid | M54: =IF(ISNA(XLOOKUP(C54,Headcount!C:C,Headcount!C:C)),"Invalid FK","Valid") -> Valid
A55: TRX100053 | B55: 44687 | C55: -22712.23 | D55: Expense | E55: Payroll | F55: Enterprise | G55: North | I55: VEND1079 | J55: Daughter training suffer miss money. | K55: =IF(ISNA(XLOOKUP(A55,Customers!A:A,Customers!A:A)),"Invalid FK","Valid") -> Valid | L55: =IF(ISNA(XLOOKUP(B55,Vendors!A:A,Vendors!A:A)),"Invalid FK","Valid") -> Valid | M55: =IF(ISNA(XLOOKUP(C55,Headcount!C:C,Headcount!C:C)),"Invalid FK","Valid") -> Valid
A56: TRX100054 | B56: 44881 | C56: -51925.51 | D56: Expense | E56: Other | F56: Online | G56: East | I56: VEND1098 | J56: Including measure leave road leg mention. | K56: =IF(ISNA(XLOOKUP(A56,Customers!A:A,Customers!A:A)),"Invalid FK","Valid") -> Valid | L56: =IF(ISNA(XLOOKUP(B56,Vendors!A:A,Vendors!A:A)),"Invalid FK","Valid") -> Valid | M56: =IF(ISNA(XLOOKUP(C56,Headcount!C:C,Headcount!C:C)),"Invalid FK","Valid") -> Valid
A57: TRX100055 | B57: 44960 | C57: -42768.16 | D57: Expense | E57: Rent | F57: Online | G57: North | I57: VEND1082 | J57: Technology far reach thought probably cover increase. | K57: =IF(ISNA(XLOOKUP(A57,Customers!A:A,Customers!A:A)),"Invalid FK","Valid") -> Valid | L57: =IF(ISNA(XLOOKUP(B57,Vendors!A:A,Vendors!A:A)),"Invalid FK","Valid") -> Valid | M57: =IF(ISNA(XLOOKUP(C57,Headcount!C:C,Headcount!C:C)),"Invalid FK","Valid") -> Valid
A58: TRX100056 | B58: 44655 | C58: -22339.95 | D58: Expense | E58: Marketing | F58: Retail | G58: East | I58: VEND1001 | J58: Play prepare red goal. | K58: =IF(ISNA(XLOOKUP(A58,Customers!A:A,Customers!A:A)),"Invalid FK","Valid") -> Valid | L58: =IF(ISNA(XLOOKUP(B58,Vendors!A:A,Vendors!A:A)),"Invalid FK","Valid") -> Valid | M58: =IF(ISNA(XLOOKUP(C58,Headcount!C:C,Headcount!C:C)),"Invalid FK","Valid") -> Valid
A59: TRX100057 | B59: 44995 | C59: -43856.82 | D59: Expense | E59: Utilities | F59: Enterprise | G59: West | I59: VEND1042 | J59: Hard this despite certain they both provide machine. | K59: =IF(ISNA(XLOOKUP(A59,Customers!A:A,Customers!A:A)),"Invalid FK","Valid") -> Valid | L59: =IF(ISNA(XLOOKUP(B59,Vendors!A:A,Vendors!A:A)),"Invalid FK","Valid") -> Valid | M59: =IF(ISNA(XLOOKUP(C59,Headcount!C:C,Headcount!C:C)),"Invalid FK","Valid") -> Valid
A60: TRX100058 | B60: 44730 | C60: 86224.06 | D60: Revenue | E60: Product | F60: Retail | G60: East | H60: CUST10151 | J60: Summer everyone his magazine six value week. | K60: =IF(ISNA(XLOOKUP(A60,Customers!A:A,Customers!A:A)),"Invalid FK","Valid") -> Valid | L60: =IF(ISNA(XLOOKUP(B60,Vendors!A:A,Vendors!A:A)),"Invalid FK","Valid") -> Valid | M60: =IF(ISNA(XLOOKUP(C60,Headcount!C:C,Headcount!C:C)),"Invalid FK","Valid") -> Valid
A61: TRX100059 | B61: 44818 | C61: 196305.77 | D61: Revenue | E61: Service | F61: Enterprise | G61: West | H61: CUST10016 | J61: Pm like matter price personal for. | K61: =IF(ISNA(XLOOKUP(A61,Customers!A:A,Customers!A:A)),"Invalid FK","Valid") -> Valid | L61: =IF(ISNA(XLOOKUP(B61,Vendors!A:A,Vendors!A:A)),"Invalid FK","Valid") -> Valid | M61: =IF(ISNA(XLOOKUP(C61,Headcount!C:C,Headcount!C:C)),"Invalid FK","Valid") -> Valid
A62: TRX100060 | B62: 45271 | C62: 144148.9 | D62: Revenue | E62: Product | F62: Online | G62: South | H62: CUST10049 | J62: True shoulder away. | K62: =IF(ISNA(XLOOKUP(A62,Customers!A:A,Customers!A:A)),"Invalid FK","Valid") -> Valid | L62: =IF(ISNA(XLOOKUP(B62,Vendors!A:A,Vendors!A:A)),"Invalid FK","Valid") -> Valid | M62: =IF(ISNA(XLOOKUP(C62,Headcount!C:C,Headcount!C:C)),"Invalid FK","Valid") -> Valid
A63: TRX100061 | B63: 44872 | C63: 161193.89 | D63: Revenue | E63: Product | F63: Online | G63: South | H63: CUST10129 | J63: Page truth although under for water analysis. | K63: =IF(ISNA(XLOOKUP(A63,Customers!A:A,Customers!A:A)),"Invalid FK","Valid") -> Valid | L63: =IF(ISNA(XLOOKUP(B63,Vendors!A:A,Vendors!A:A)),"Invalid FK","Valid") -> Valid | M63: =IF(ISNA(XLOOKUP(C63,Headcount!C:C,Headcount!C:C)),"Invalid FK","Valid") -> Valid
A64: TRX100062 | B64: 44808 | C64: 157413.67 | D64: Revenue | E64: Service | F64: Online | G64: West | H64: CUST10183 | J64: Early choice speech follow fund measure. | K64: =IF(ISNA(XLOOKUP(A64,Customers!A:A,Customers!A:A)),"Invalid FK","Valid") -> Valid | L64: =IF(ISNA(XLOOKUP(B64,Vendors!A:A,Vendors!A:A)),"Invalid FK","Valid") -> Valid | M64: =IF(ISNA(XLOOKUP(C64,Headcount!C:C,Headcount!C:C)),"Invalid FK","Valid") -> Valid
A65: TRX100063 | B65: 44583 | C65: 113690.25 | D65: Revenue | E65: Subscription | F65: Enterprise | G65: West | H65: CUST10348 | J65: Same whether interesting half Republican. | K65: =IF(ISNA(XLOOKUP(A65,Customers!A:A,Customers!A:A)),"Invalid FK","Valid") -> Valid | L65: =IF(ISNA(XLOOKUP(B65,Vendors!A:A,Vendors!A:A)),"Invalid FK","Valid") -> Valid | M65: =IF(ISNA(XLOOKUP(C65,Headcount!C:C,Headcount!C:C)),"Invalid FK","Valid") -> Valid
A66: TRX100064 | B66: 45152 | C66: 194267.47 | D66: Revenue | E66: Subscription | F66: Online | G66: East | H66: CUST10075 | J66: Half toward his. | K66: =IF(ISNA(XLOOKUP(A66,Customers!A:A,Customers!A:A)),"Invalid FK","Valid") -> Valid | L66: =IF(ISNA(XLOOKUP(B66,Vendors!A:A,Vendors!A:A)),"Invalid FK","Valid") -> Valid | M66: =IF(ISNA(XLOOKUP(C66,Headcount!C:C,Headcount!C:C)),"Invalid FK","Valid") -> Valid
A67: TRX100065 | B67: 45018 | C67: -53590.9 | D67: Expense | E67: Marketing | F67: Enterprise | G67: South | I67: VEND1107 | J67: Source learn expect show. | K67: =IF(ISNA(XLOOKUP(A67,Customers!A:A,Customers!A:A)),"Invalid FK","Valid") -> Valid | L67: =IF(ISNA(XLOOKUP(B67,Vendors!A:A,Vendors!A:A)),"Invalid FK","Valid") -> Valid | M67: =IF(ISNA(XLOOKUP(C67,Headcount!C:C,Headcount!C:C)),"Invalid FK","Valid") -> Valid
A68: TRX100066 | B68: 44844 | C68: -29061.06 | D68: Expense | E68: Other | F68: Retail | G68: North | I68: VEND1019 | J68: House performance sign deep. | K68: =IF(ISNA(XLOOKUP(A68,Customers!A:A,Customers!A:A)),"Invalid FK","Valid") -> Valid | L68: =IF(ISNA(XLOOKUP(B68,Vendors!A:A,Vendors!A:A)),"Invalid FK","Valid") -> Valid | M68: =IF(ISNA(XLOOKUP(C68,Headcount!C:C,Headcount!C:C)),"Invalid FK","Valid") -> Valid
A69: TRX100067 | B69: 44904 | C69: -48080.35 | D69: Expense | E69: Rent | F69: Retail | G69: North | I69: VEND1030 | J69: Home now local perform by. | K69: =IF(ISNA(XLOOKUP(A69,Customers!A:A,Customers!A:A)),"Invalid FK","Valid") -> Valid | L69: =IF(ISNA(XLOOKUP(B69,Vendors!A:A,Vendors!A:A)),"Invalid FK","Valid") -> Valid | M69: =IF(ISNA(XLOOKUP(C69,Headcount!C:C,Headcount!C:C)),"Invalid FK","Valid") -> Valid
A70: TRX100068 | B70: 44749 | C70: 218024.69 | D70: Revenue | E70: Product | F70: Online | G70: North | H70: CUST10321 | J70: Dog eight perhaps audience past eye. | K70: =IF(ISNA(XLOOKUP(A70,Customers!A:A,Customers!A:A)),"Invalid FK","Valid") -> Valid | L70: =IF(ISNA(XLOOKUP(B70,Vendors!A:A,Vendors!A:A)),"Invalid FK","Valid") -> Valid | M70: =IF(ISNA(XLOOKUP(C70,Headcount!C:C,Headcount!C:C)),"Invalid FK","Valid") -> Valid
A71: TRX100069 | B71: 44749 | C71: -38127.82 | D71: Expense | E71: Rent | F71: Enterprise | G71: West | I71: VEND1086 | J71: His another government threat choose water fear. | K71: =IF(ISNA(XLOOKUP(A71,Customers!A:A,Customers!A:A)),"Invalid FK","Valid") -> Valid | L71: =IF(ISNA(XLOOKUP(B71,Vendors!A:A,Vendors!A:A)),"Invalid FK","Valid") -> Valid | M71: =IF(ISNA(XLOOKUP(C71,Headcount!C:C,Headcount!C:C)),"Invalid FK","Valid") -> Valid
A72: TRX100070 | B72: 44989 | C72: -31873.97 | D72: Expense | E72: Rent | F72: Retail | G72: North | I72: VEND1086 | J72: Enjoy keep pass write state even bank. | K72: =IF(ISNA(XLOOKUP(A72,Customers!A:A,Customers!A:A)),"Invalid FK","Valid") -> Valid | L72: =IF(ISNA(XLOOKUP(B72,Vendors!A:A,Vendors!A:A)),"Invalid FK","Valid") -> Valid | M72: =IF(ISNA(XLOOKUP(C72,Headcount!C:C,Headcount!C:C)),"Invalid FK","Valid") -> Valid
A73: TRX100071 | B73: 45082 | C73: 203084.24 | D73: Revenue | E73: Subscription | F73: Online | G73: West | H73: CUST10116 | J73: Possible talk model why we town decade. | K73: =IF(ISNA(XLOOKUP(A73,Customers!A:A,Customers!A:A)),"Invalid FK","Valid") -> Valid | L73: =IF(ISNA(XLOOKUP(B73,Vendors!A:A,Vendors!A:A)),"Invalid FK","Valid") -> Valid | M73: =IF(ISNA(XLOOKUP(C73,Headcount!C:C,Headcount!C:C)),"Invalid FK","Valid") -> Valid
A74: TRX100072 | B74: 45290 | C74: 222948.96 | D74: Revenue | E74: Subscription | F74: Online | G74: North | H74: CUST10063 | J74: Black sit anyone language song show watch better. | K74: =IF(ISNA(XLOOKUP(A74,Customers!A:A,Customers!A:A)),"Invalid FK","Valid") -> Valid | L74: =IF(ISNA(XLOOKUP(B74,Vendors!A:A,Vendors!A:A)),"Invalid FK","Valid") -> Valid | M74: =IF(ISNA(XLOOKUP(C74,Headcount!C:C,Headcount!C:C)),"Invalid FK","Valid") -> Valid
A75: TRX100073 | B75: 45270 | C75: 238667.54 | D75: Revenue | E75: Product | F75: Enterprise | G75: South | H75: CUST10137 | J75: Rate reflect building guess well TV. | K75: =IF(ISNA(XLOOKUP(A75,Customers!A:A,Customers!A:A)),"Invalid FK","Valid") -> Valid | L75: =IF(ISNA(XLOOKUP(B75,Vendors!A:A,Vendors!A:A)),"Invalid FK","Valid") -> Valid | M75: =IF(ISNA(XLOOKUP(C75,Headcount!C:C,Headcount!C:C)),"Invalid FK","Valid") -> Valid
A76: TRX100074 | B76: 44673 | C76: 132774.78 | D76: Revenue | E76: Subscription | F76: Retail | G76: South | H76: CUST10298 | J76: And stop raise somebody nice. | K76: =IF(ISNA(XLOOKUP(A76,Customers!A:A,Customers!A:A)),"Invalid FK","Valid") -> Valid | L76: =IF(ISNA(XLOOKUP(B76,Vendors!A:A,Vendors!A:A)),"Invalid FK","Valid") -> Valid | M76: =IF(ISNA(XLOOKUP(C76,Headcount!C:C,Headcount!C:C)),"Invalid FK","Valid") -> Valid
A77: TRX100075 | B77: 45186 | C77: 188545.69 | D77: Revenue | E77: Subscription | F77: Enterprise | G77: North | H77: CUST10187 | J77: Wonder increase hundred today final debate. | K77: =IF(ISNA(XLOOKUP(A77,Customers!A:A,Customers!A:A)),"Invalid FK","Valid") -> Valid | L77: =IF(ISNA(XLOOKUP(B77,Vendors!A:A,Vendors!A:A)),"Invalid FK","Valid") -> Valid | M77: =IF(ISNA(XLOOKUP(C77,Headcount!C:C,Headcount!C:C)),"Invalid FK","Valid") -> Valid
A78: TRX100076 | B78: 45056 | C78: 138240.93 | D78: Revenue | E78: Service | F78: Retail | G78: East | H78: CUST10285 | J78: Pick fast one entire. | K78: =IF(ISNA(XLOOKUP(A78,Customers!A:A,Customers!A:A)),"Invalid FK","Valid") -> Valid | L78: =IF(ISNA(XLOOKUP(B78,Vendors!A:A,Vendors!A:A)),"Invalid FK","Valid") -> Valid | M78: =IF(ISNA(XLOOKUP(C78,Headcount!C:C,Headcount!C:C)),"Invalid FK","Valid") -> Valid
A79: TRX100077 | B79: 45149 | C79: -14341.81 | D79: Expense | E79: Payroll | F79: Online | G79: North | I79: VEND1095 | J79: East very manager set act perhaps company ability. | K79: =IF(ISNA(XLOOKUP(A79,Customers!A:A,Customers!A:A)),"Invalid FK","Valid") -> Valid | L79: =IF(ISNA(XLOOKUP(B79,Vendors!A:A,Vendors!A:A)),"Invalid FK","Valid") -> Valid | M79: =IF(ISNA(XLOOKUP(C79,Headcount!C:C,Headcount!C:C)),"Invalid FK","Valid") -> Valid
A80: TRX100078 | B80: 44904 | C80: 163678.6 | D80: Revenue | E80: Product | F80: Enterprise | G80: West | H80: CUST10207 | J80: Three specific late economic serious word. | K80: =IF(ISNA(XLOOKUP(A80,Customers!A:A,Customers!A:A)),"Invalid FK","Valid") -> Valid | L80: =IF(ISNA(XLOOKUP(B80,Vendors!A:A,Vendors!A:A)),"Invalid FK","Valid") -> Valid | M80: =IF(ISNA(XLOOKUP(C80,Headcount!C:C,Headcount!C:C)),"Invalid FK","Valid") -> Valid
A81: TRX100079 | B81: 44851 | C81: 198317.9 | D81: Revenue | E81: Product | F81: Enterprise | G81: West | H81: CUST10207 | J81: Continue beyond suffer plant student. | K81: =IF(ISNA(XLOOKUP(A81,Customers!A:A,Customers!A:A)),"Invalid FK","Valid") -> Valid | L81: =IF(ISNA(XLOOKUP(B81,Vendors!A:A,Vendors!A:A)),"Invalid FK","Valid") -> Valid | M81: =IF(ISNA(XLOOKUP(C81,Headcount!C:C,Headcount!C:C)),"Invalid FK","Valid") -> Valid
A82: TRX100080 | B82: 45153 | C82: 188616.88 | D82: Revenue | E82: Product | F82: Retail | G82: North | H82: CUST10108 | J82: Doctor surface girl friend everybody thousand under. | K82: =IF(ISNA(XLOOKUP(A82,Customers!A:A,Customers!A:A)),"Invalid FK","Valid") -> Valid | L82: =IF(ISNA(XLOOKUP(B82,Vendors!A:A,Vendors!A:A)),"Invalid FK","Valid") -> Valid | M82: =IF(ISNA(XLOOKUP(C82,Headcount!C:C,Headcount!C:C)),"Invalid FK","Valid") -> Valid
A83: TRX100081 | B83: 44738 | C83: -25218.03 | D83: Expense | E83: Marketing | F83: Online | G83: East | I83: VEND1089 | J83: Kid item feeling less player. | K83: =IF(ISNA(XLOOKUP(A83,Customers!A:A,Customers!A:A)),"Invalid FK","Valid") -> Valid | L83: =IF(ISNA(XLOOKUP(B83,Vendors!A:A,Vendors!A:A)),"Invalid FK","Valid") -> Valid | M83: =IF(ISNA(XLOOKUP(C83,Headcount!C:C,Headcount!C:C)),"Invalid FK","Valid") -> Valid
A84: TRX100082 | B84: 45196 | C84: -15892.26 | D84: Expense | E84: Supplies | F84: Enterprise | G84: South | I84: VEND1025 | J84: Increase mouth your indeed. | K84: =IF(ISNA(XLOOKUP(A84,Customers!A:A,Customers!A:A)),"Invalid FK","Valid") -> Valid | L84: =IF(ISNA(XLOOKUP(B84,Vendors!A:A,Vendors!A:A)),"Invalid FK","Valid") -> Valid | M84: =IF(ISNA(XLOOKUP(C84,Headcount!C:C,Headcount!C:C)),"Invalid FK","Valid") -> Valid
A85: TRX100083 | B85: 44807 | C85: 199974.44 | D85: Revenue | E85: Subscription | F85: Enterprise | G85: South | H85: CUST10092 | J85: Letter along six agent staff industry who. | K85: =IF(ISNA(XLOOKUP(A85,Customers!A:A,Customers!A:A)),"Invalid FK","Valid") -> Valid | L85: =IF(ISNA(XLOOKUP(B85,Vendors!A:A,Vendors!A:A)),"Invalid FK","Valid") -> Valid | M85: =IF(ISNA(XLOOKUP(C85,Headcount!C:C,Headcount!C:C)),"Invalid FK","Valid") -> Valid
A86: TRX100084 | B86: 44686 | C86: 128923.58 | D86: Revenue | E86: Service | F86: Enterprise | G86: North | H86: CUST10082 | J86: Cell prevent goal view water shake matter effect. | K86: =IF(ISNA(XLOOKUP(A86,Customers!A:A,Customers!A:A)),"Invalid FK","Valid") -> Valid | L86: =IF(ISNA(XLOOKUP(B86,Vendors!A:A,Vendors!A:A)),"Invalid FK","Valid") -> Valid | M86: =IF(ISNA(XLOOKUP(C86,Headcount!C:C,Headcount!C:C)),"Invalid FK","Valid") -> Valid
A87: TRX100085 | B87: 44982 | C87: 67222.23 | D87: Revenue | E87: Service | F87: Online | G87: West | H87: CUST10209 | J87: End cover a enough speak figure. | K87: =IF(ISNA(XLOOKUP(A87,Customers!A:A,Customers!A:A)),"Invalid FK","Valid") -> Valid | L87: =IF(ISNA(XLOOKUP(B87,Vendors!A:A,Vendors!A:A)),"Invalid FK","Valid") -> Valid | M87: =IF(ISNA(XLOOKUP(C87,Headcount!C:C,Headcount!C:C)),"Invalid FK","Valid") -> Valid
A88: TRX100086 | B88: 44923 | C88: 186952.56 | D88: Revenue | E88: Subscription | F88: Online | G88: West | H88: CUST10089 | J88: Economic behind young American artist main personal. | K88: =IF(ISNA(XLOOKUP(A88,Customers!A:A,Customers!A:A)),"Invalid FK","Valid") -> Valid | L88: =IF(ISNA(XLOOKUP(B88,Vendors!A:A,Vendors!A:A)),"Invalid FK","Valid") -> Valid | M88: =IF(ISNA(XLOOKUP(C88,Headcount!C:C,Headcount!C:C)),"Invalid FK","Valid") -> Valid
A89: TRX100087 | B89: 45116 | C89: 164462.06 | D89: Revenue | E89: Service | F89: Retail | G89: East | H89: CUST10042 | J89: Girl reveal order deep chair cut sit. | K89: =IF(ISNA(XLOOKUP(A89,Customers!A:A,Customers!A:A)),"Invalid FK","Valid") -> Valid | L89: =IF(ISNA(XLOOKUP(B89,Vendors!A:A,Vendors!A:A)),"Invalid FK","Valid") -> Valid | M89: =IF(ISNA(XLOOKUP(C89,Headcount!C:C,Headcount!C:C)),"Invalid FK","Valid") -> Valid
A90: TRX100088 | B90: 44872 | C90: 18077.56 | D90: Equity | E90: Equity | F90: Enterprise | G90: South | J90: Once fact interest difference section remain. | K90: =IF(ISNA(XLOOKUP(A90,Customers!A:A,Customers!A:A)),"Invalid FK","Valid") -> Valid | L90: =IF(ISNA(XLOOKUP(B90,Vendors!A:A,Vendors!A:A)),"Invalid FK","Valid") -> Valid | M90: =IF(ISNA(XLOOKUP(C90,Headcount!C:C,Headcount!C:C)),"Invalid FK","Valid") -> Valid
A91: TRX100089 | B91: 45213 | C91: 72337.28 | D91: Revenue | E91: Service | F91: Online | G91: South | H91: CUST10157 | J91: Able finish they defense yet activity. | K91: =IF(ISNA(XLOOKUP(A91,Customers!A:A,Customers!A:A)),"Invalid FK","Valid") -> Valid | L91: =IF(ISNA(XLOOKUP(B91,Vendors!A:A,Vendors!A:A)),"Invalid FK","Valid") -> Valid | M91: =IF(ISNA(XLOOKUP(C91,Headcount!C:C,Headcount!C:C)),"Invalid FK","Valid") -> Valid
A92: TRX100090 | B92: 44760 | C92: -40667.5 | D92: Expense | E92: Rent | F92: Online | G92: South | I92: VEND1090 | J92: Instead age animal popular parent baby. | K92: =IF(ISNA(XLOOKUP(A92,Customers!A:A,Customers!A:A)),"Invalid FK","Valid") -> Valid | L92: =IF(ISNA(XLOOKUP(B92,Vendors!A:A,Vendors!A:A)),"Invalid FK","Valid") -> Valid | M92: =IF(ISNA(XLOOKUP(C92,Headcount!C:C,Headcount!C:C)),"Invalid FK","Valid") -> Valid
A93: TRX100091 | B93: 44565 | C93: 177006.22 | D93: Revenue | E93: Product | F93: Retail | G93: West | H93: CUST10212 | J93: Choose per range week. | K93: =IF(ISNA(XLOOKUP(A93,Customers!A:A,Customers!A:A)),"Invalid FK","Valid") -> Valid | L93: =IF(ISNA(XLOOKUP(B93,Vendors!A:A,Vendors!A:A)),"Invalid FK","Valid") -> Valid | M93: =IF(ISNA(XLOOKUP(C93,Headcount!C:C,Headcount!C:C)),"Invalid FK","Valid") -> Valid
A94: TRX100092 | B94: 44759 | C94: -33821.98 | D94: Expense | E94: Other | F94: Online | G94: West | I94: VEND1059 | J94: Lay buy bar century. | K94: =IF(ISNA(XLOOKUP(A94,Customers!A:A,Customers!A:A)),"Invalid FK","Valid") -> Valid | L94: =IF(ISNA(XLOOKUP(B94,Vendors!A:A,Vendors!A:A)),"Invalid FK","Valid") -> Valid | M94: =IF(ISNA(XLOOKUP(C94,Headcount!C:C,Headcount!C:C)),"Invalid FK","Valid") -> Valid
A95: TRX100093 | B95: 44749 | C95: 113760.1 | D95: Revenue | E95: Service | F95: Enterprise | G95: South | H95: CUST10232 | J95: Congress whose main matter coach loss executive. | K95: =IF(ISNA(XLOOKUP(A95,Customers!A:A,Customers!A:A)),"Invalid FK","Valid") -> Valid | L95: =IF(ISNA(XLOOKUP(B95,Vendors!A:A,Vendors!A:A)),"Invalid FK","Valid") -> Valid | M95: =IF(ISNA(XLOOKUP(C95,Headcount!C:C,Headcount!C:C)),"Invalid FK","Valid") -> Valid
A96: TRX100094 | B96: 44618 | C96: 68040.32 | D96: Revenue | E96: Service | F96: Retail | G96: South | H96: CUST10121 | J96: Bar rock democratic positive live easy grow. | K96: =IF(ISNA(XLOOKUP(A96,Customers!A:A,Customers!A:A)),"Invalid FK","Valid") -> Valid | L96: =IF(ISNA(XLOOKUP(B96,Vendors!A:A,Vendors!A:A)),"Invalid FK","Valid") -> Valid | M96: =IF(ISNA(XLOOKUP(C96,Headcount!C:C,Headcount!C:C)),"Invalid FK","Valid") -> Valid
A97: TRX100095 | B97: 45132 | C97: 114168.76 | D97: Revenue | E97: Product | F97: Retail | G97: West | H97: CUST10237 | J97: Certainly believe white money. | K97: =IF(ISNA(XLOOKUP(A97,Customers!A:A,Customers!A:A)),"Invalid FK","Valid") -> Valid | L97: =IF(ISNA(XLOOKUP(B97,Vendors!A:A,Vendors!A:A)),"Invalid FK","Valid") -> Valid | M97: =IF(ISNA(XLOOKUP(C97,Headcount!C:C,Headcount!C:C)),"Invalid FK","Valid") -> Valid
A98: TRX100096 | B98: 45034 | C98: 104796.05 | D98: Revenue | E98: Product | F98: Online | G98: West | H98: CUST10266 | J98: Support visit else lead call. | K98: =IF(ISNA(XLOOKUP(A98,Customers!A:A,Customers!A:A)),"Invalid FK","Valid") -> Valid | L98: =IF(ISNA(XLOOKUP(B98,Vendors!A:A,Vendors!A:A)),"Invalid FK","Valid") -> Valid | M98: =IF(ISNA(XLOOKUP(C98,Headcount!C:C,Headcount!C:C)),"Invalid FK","Valid") -> Valid
A99: TRX100097 | B99: 44637 | C99: -40864.74 | D99: Expense | E99: Other | F99: Retail | G99: East | I99: VEND1072 | J99: But share truth conference seem TV. | K99: =IF(ISNA(XLOOKUP(A99,Customers!A:A,Customers!A:A)),"Invalid FK","Valid") -> Valid | L99: =IF(ISNA(XLOOKUP(B99,Vendors!A:A,Vendors!A:A)),"Invalid FK","Valid") -> Valid | M99: =IF(ISNA(XLOOKUP(C99,Headcount!C:C,Headcount!C:C)),"Invalid FK","Valid") -> Valid
A100: TRX100098 | B100: 45167 | C100: -10569.47 | D100: Expense | E100: Supplies | F100: Retail | G100: East | I100: VEND1065 | J100: Officer agree interesting nice risk from medical some. | K100: =IF(ISNA(XLOOKUP(A100,Customers!A:A,Customers!A:A)),"Invalid FK","Valid") -> Valid | L100: =IF(ISNA(XLOOKUP(B100,Vendors!A:A,Vendors!A:A)),"Invalid FK","Valid") -> Valid | M100: =IF(ISNA(XLOOKUP(C100,Headcount!C:C,Headcount!C:C)),"Invalid FK","Valid") -> Valid
...

Sheet Financial_Transactions_Clean
A1: transaction_id | B1: transaction_date | C1: amount | D1: account_type | E1: category | F1: business_unit | G1: region | H1: customer_id | I1: vendor_id | J1: description | K1: customer_fk_check | L1: vendor_fk_check | M1: headcount_fk_check | N1: missing_flag | O1: outlier_flag | P1: validation_status
A2: TRX100000 | B2: 45172 | C2: -66631.73 | D2: Expense | E2: Supplies | F2: Online | G2: West | I2: VEND1053 | J2: Begin Catch Control Dark Practice. | K2: Valid | L2: Valid | M2: Valid | N2: =IF(OR(B2="",C2="",D2="",F2=""),"Missing","OK") -> OK | O2: =IF(OR(Table1_17[[#This Row],[amount]]<$Y$8,Table1_17[[#This Row],[amount]]>$Y$7),"Outlier","Normal") -> Normal | P2: =IF(OR(Table1_17[[#This Row],[missing_flag]]="Missing",Table1_17[[#This Row],[outlier_flag]]="Outliers"),"Review","Valid") -> Valid | X2: Q1 = | Y2: =_xlfn.QUARTILE.EXC(C:C,1) -> -33703.118
A3: TRX100001 | B3: 45182 | C3: -54305.58 | D3: Expense | E3: Utilities | F3: Enterprise | G3: East | I3: VEND1059 | J3: Style Guy Soldier Boy Energy Above. | K3: Valid | L3: Valid | M3: Valid | N3: =IF(OR(B3="",C3="",D3="",F3=""),"Missing","OK") -> OK | O3: =IF(OR(Table1_17[[#This Row],[amount]]<$Y$8,Table1_17[[#This Row],[amount]]>$Y$7),"Outlier","Normal") -> Normal | P3: =IF(OR(Table1_17[[#This Row],[missing_flag]]="Missing",Table1_17[[#This Row],[outlier_flag]]="Outliers"),"Review","Valid") -> Valid | X3: Q3 = | Y3: =_xlfn.QUARTILE.EXC(C:C,3) -> 157304.32
A4: TRX100002 | B4: 45104 | C4: 146074.92 | D4: Revenue | E4: Subscription | F4: Online | G4: East | H4: CUST10122 | J4: Skill Surface Drug Personal Western. | K4: Valid | L4: Valid | M4: Valid | N4: =IF(OR(B4="",C4="",D4="",F4=""),"Missing","OK") -> OK | O4: =IF(OR(Table1_17[[#This Row],[amount]]<$Y$8,Table1_17[[#This Row],[amount]]>$Y$7),"Outlier","Normal") -> Normal | P4: =IF(OR(Table1_17[[#This Row],[missing_flag]]="Missing",Table1_17[[#This Row],[outlier_flag]]="Outliers"),"Review","Valid") -> Valid
A5: TRX100003 | B5: 45102 | C5: 212157.95 | D5: Revenue | E5: Service | F5: Enterprise | G5: West | H5: CUST10027 | J5: Develop Many It I Rich Floor Decide. | K5: Valid | L5: Valid | M5: Valid | N5: =IF(OR(B5="",C5="",D5="",F5=""),"Missing","OK") -> OK | O5: =IF(OR(Table1_17[[#This Row],[amount]]<$Y$8,Table1_17[[#This Row],[amount]]>$Y$7),"Outlier","Normal") -> Normal | P5: =IF(OR(Table1_17[[#This Row],[missing_flag]]="Missing",Table1_17[[#This Row],[outlier_flag]]="Outliers"),"Review","Valid") -> Valid | X5: IQR = | Y5: =Y3-Y2 -> 191007.43
A6: TRX100004 | B6: 45245 | C6: -35944.73 | D6: Expense | E6: Rent | F6: Enterprise | G6: North | I6: VEND1046 | J6: Choose Thought Teach Never. | K6: Valid | L6: Valid | M6: Valid | N6: =IF(OR(B6="",C6="",D6="",F6=""),"Missing","OK") -> OK | O6: =IF(OR(Table1_17[[#This Row],[amount]]<$Y$8,Table1_17[[#This Row],[amount]]>$Y$7),"Outlier","Normal") -> Normal | P6: =IF(OR(Table1_17[[#This Row],[missing_flag]]="Missing",Table1_17[[#This Row],[outlier_flag]]="Outliers"),"Review","Valid") -> Valid
A7: TRX100005 | B7: 44989 | C7: 90953.83 | D7: Revenue | E7: Service | F7: Retail | G7: South | H7: CUST10332 | J7: Dinner Present Unit Lay Course. | K7: Valid | L7: Valid | M7: Valid | N7: =IF(OR(B7="",C7="",D7="",F7=""),"Missing","OK") -> OK | O7: =IF(OR(Table1_17[[#This Row],[amount]]<$Y$8,Table1_17[[#This Row],[amount]]>$Y$7),"Outlier","Normal") -> Normal | P7: =IF(OR(Table1_17[[#This Row],[missing_flag]]="Missing",Table1_17[[#This Row],[outlier_flag]]="Outliers"),"Review","Valid") -> Valid | X7: Upper Limit = | Y7: =Y3+1.5*Y5 -> 443815.47
A8: TRX100006 | B8: 45115 | C8: 73251.21 | D8: Revenue | E8: Service | F8: Online | G8: West | H8: CUST10270 | J8: Data Ago Arm Care Hundred Represent Wonder. | K8: Valid | L8: Valid | M8: Valid | N8: =IF(OR(B8="",C8="",D8="",F8=""),"Missing","OK") -> OK | O8: =IF(OR(Table1_17[[#This Row],[amount]]<$Y$8,Table1_17[[#This Row],[amount]]>$Y$7),"Outlier","Normal") -> Normal | P8: =IF(OR(Table1_17[[#This Row],[missing_flag]]="Missing",Table1_17[[#This Row],[outlier_flag]]="Outliers"),"Review","Valid") -> Valid | X8: Lower Limit = | Y8: =Y2-1.5*Y5 -> -320214.27
A9: TRX100007 | B9: 44644 | C9: -21064.02 | D9: Expense | E9: Marketing | F9: Online | G9: East | I9: VEND1115 | J9: Sign Such Remember Range Ability. | K9: Valid | L9: Valid | M9: Valid | N9: =IF(OR(B9="",C9="",D9="",F9=""),"Missing","OK") -> OK | O9: =IF(OR(Table1_17[[#This Row],[amount]]<$Y$8,Table1_17[[#This Row],[amount]]>$Y$7),"Outlier","Normal") -> Normal | P9: =IF(OR(Table1_17[[#This Row],[missing_flag]]="Missing",Table1_17[[#This Row],[outlier_flag]]="Outliers"),"Review","Valid") -> Valid
A10: TRX100008 | B10: 44775 | C10: 136347.73 | D10: Revenue | E10: Product | F10: Retail | G10: West | H10: CUST10168 | J10: Poor Similar Feeling Close Require Probably Rather Thought. | K10: Valid | L10: Valid | M10: Valid | N10: =IF(OR(B10="",C10="",D10="",F10=""),"Missing","OK") -> OK | O10: =IF(OR(Table1_17[[#This Row],[amount]]<$Y$8,Table1_17[[#This Row],[amount]]>$Y$7),"Outlier","Normal") -> Normal | P10: =IF(OR(Table1_17[[#This Row],[missing_flag]]="Missing",Table1_17[[#This Row],[outlier_flag]]="Outliers"),"Review","Valid") -> Valid
A11: TRX100009 | B11: 45094 | C11: 159482 | D11: Revenue | E11: Product | F11: Retail | G11: West | H11: CUST10151 | J11: Cause Worker Statement Office Able Foot. | K11: Valid | L11: Valid | M11: Valid | N11: =IF(OR(B11="",C11="",D11="",F11=""),"Missing","OK") -> OK | O11: =IF(OR(Table1_17[[#This Row],[amount]]<$Y$8,Table1_17[[#This Row],[amount]]>$Y$7),"Outlier","Normal") -> Normal | P11: =IF(OR(Table1_17[[#This Row],[missing_flag]]="Missing",Table1_17[[#This Row],[outlier_flag]]="Outliers"),"Review","Valid") -> Valid
A12: TRX100010 | B12: 44749 | C12: 15882.36 | D12: Equity | E12: Equity | F12: Retail | G12: South | J12: Ready Enter Quite Attack Resource List Commercial. | K12: Valid | L12: Valid | M12: Valid | N12: =IF(OR(B12="",C12="",D12="",F12=""),"Missing","OK") -> OK | O12: =IF(OR(Table1_17[[#This Row],[amount]]<$Y$8,Table1_17[[#This Row],[amount]]>$Y$7),"Outlier","Normal") -> Normal | P12: =IF(OR(Table1_17[[#This Row],[missing_flag]]="Missing",Table1_17[[#This Row],[outlier_flag]]="Outliers"),"Review","Valid") -> Valid
A13: TRX100011 | B13: 44781 | C13: 217487.82 | D13: Revenue | E13: Product | F13: Online | G13: North | H13: CUST10353 | J13: Before Green Media Feeling Mr Half Trouble. | K13: Valid | L13: Valid | M13: Valid | N13: =IF(OR(B13="",C13="",D13="",F13=""),"Missing","OK") -> OK | O13: =IF(OR(Table1_17[[#This Row],[amount]]<$Y$8,Table1_17[[#This Row],[amount]]>$Y$7),"Outlier","Normal") -> Normal | P13: =IF(OR(Table1_17[[#This Row],[missing_flag]]="Missing",Table1_17[[#This Row],[outlier_flag]]="Outliers"),"Review","Valid") -> Valid
A14: TRX100012 | B14: 45001 | C14: -8913.27 | D14: Expense | E14: Other | F14: Enterprise | G14: East | I14: VEND1067 | J14: Rise Discover Visit Security End Buy Medical Think. | K14: Valid | L14: Valid | M14: Valid | N14: =IF(OR(B14="",C14="",D14="",F14=""),"Missing","OK") -> OK | O14: =IF(OR(Table1_17[[#This Row],[amount]]<$Y$8,Table1_17[[#This Row],[amount]]>$Y$7),"Outlier","Normal") -> Normal | P14: =IF(OR(Table1_17[[#This Row],[missing_flag]]="Missing",Table1_17[[#This Row],[outlier_flag]]="Outliers"),"Review","Valid") -> Valid
A15: TRX100013 | B15: 45270 | C15: 139523.96 | D15: Revenue | E15: Service | F15: Retail | G15: North | H15: CUST10243 | J15: Military Line Exist Little Education Family World. | K15: Valid | L15: Valid | M15: Valid | N15: =IF(OR(B15="",C15="",D15="",F15=""),"Missing","OK") -> OK | O15: =IF(OR(Table1_17[[#This Row],[amount]]<$Y$8,Table1_17[[#This Row],[amount]]>$Y$7),"Outlier","Normal") -> Normal | P15: =IF(OR(Table1_17[[#This Row],[missing_flag]]="Missing",Table1_17[[#This Row],[outlier_flag]]="Outliers"),"Review","Valid") -> Valid
A16: TRX100014 | B16: 45125 | C16: 165589.04 | D16: Revenue | E16: Service | F16: Online | G16: East | H16: CUST10357 | J16: Artist Place Loss Morning. | K16: Valid | L16: Valid | M16: Valid | N16: =IF(OR(B16="",C16="",D16="",F16=""),"Missing","OK") -> OK | O16: =IF(OR(Table1_17[[#This Row],[amount]]<$Y$8,Table1_17[[#This Row],[amount]]>$Y$7),"Outlier","Normal") -> Normal | P16: =IF(OR(Table1_17[[#This Row],[missing_flag]]="Missing",Table1_17[[#This Row],[outlier_flag]]="Outliers"),"Review","Valid") -> Valid
A17: TRX100015 | B17: 44952 | C17: 262541.15 | D17: Revenue | E17: Service | F17: Retail | G17: West | H17: CUST10045 | J17: Game Evidence Support Skill Pretty. | K17: Valid | L17: Valid | M17: Valid | N17: =IF(OR(B17="",C17="",D17="",F17=""),"Missing","OK") -> OK | O17: =IF(OR(Table1_17[[#This Row],[amount]]<$Y$8,Table1_17[[#This Row],[amount]]>$Y$7),"Outlier","Normal") -> Normal | P17: =IF(OR(Table1_17[[#This Row],[missing_flag]]="Missing",Table1_17[[#This Row],[outlier_flag]]="Outliers"),"Review","Valid") -> Valid
A18: TRX100016 | B18: 45087 | C18: 152113.39 | D18: Revenue | E18: Service | F18: Online | G18: South | H18: CUST10120 | J18: Bad Author Generation Decade Increase. | K18: Valid | L18: Valid | M18: Valid | N18: =IF(OR(B18="",C18="",D18="",F18=""),"Missing","OK") -> OK | O18: =IF(OR(Table1_17[[#This Row],[amount]]<$Y$8,Table1_17[[#This Row],[amount]]>$Y$7),"Outlier","Normal") -> Normal | P18: =IF(OR(Table1_17[[#This Row],[missing_flag]]="Missing",Table1_17[[#This Row],[outlier_flag]]="Outliers"),"Review","Valid") -> Valid
A19: TRX100017 | B19: 44726 | C19: 107495.7 | D19: Revenue | E19: Service | F19: Online | G19: North | H19: CUST10228 | J19: Left Own Eat Wife Tell With. | K19: Valid | L19: Valid | M19: Valid | N19: =IF(OR(B19="",C19="",D19="",F19=""),"Missing","OK") -> OK | O19: =IF(OR(Table1_17[[#This Row],[amount]]<$Y$8,Table1_17[[#This Row],[amount]]>$Y$7),"Outlier","Normal") -> Normal | P19: =IF(OR(Table1_17[[#This Row],[missing_flag]]="Missing",Table1_17[[#This Row],[outlier_flag]]="Outliers"),"Review","Valid") -> Valid
A20: TRX100018 | B20: 45190 | C20: 83127.62 | D20: Revenue | E20: Subscription | F20: Online | G20: West | H20: CUST10333 | J20: Individual First Region. | K20: Valid | L20: Valid | M20: Valid | N20: =IF(OR(B20="",C20="",D20="",F20=""),"Missing","OK") -> OK | O20: =IF(OR(Table1_17[[#This Row],[amount]]<$Y$8,Table1_17[[#This Row],[amount]]>$Y$7),"Outlier","Normal") -> Normal | P20: =IF(OR(Table1_17[[#This Row],[missing_flag]]="Missing",Table1_17[[#This Row],[outlier_flag]]="Outliers"),"Review","Valid") -> Valid
A21: TRX100019 | B21: 44793 | C21: 145634.47 | D21: Revenue | E21: Service | F21: Enterprise | G21: West | H21: CUST10302 | J21: Rise War Shake Doctor. | K21: Valid | L21: Valid | M21: Valid | N21: =IF(OR(B21="",C21="",D21="",F21=""),"Missing","OK") -> OK | O21: =IF(OR(Table1_17[[#This Row],[amount]]<$Y$8,Table1_17[[#This Row],[amount]]>$Y$7),"Outlier","Normal") -> Normal | P21: =IF(OR(Table1_17[[#This Row],[missing_flag]]="Missing",Table1_17[[#This Row],[outlier_flag]]="Outliers"),"Review","Valid") -> Valid
A22: TRX100020 | B22: 45062 | C22: 167566.97 | D22: Revenue | E22: Service | F22: Retail | G22: North | H22: CUST10042 | J22: Before Expect Allow Job One Set. | K22: Valid | L22: Valid | M22: Valid | N22: =IF(OR(B22="",C22="",D22="",F22=""),"Missing","OK") -> OK | O22: =IF(OR(Table1_17[[#This Row],[amount]]<$Y$8,Table1_17[[#This Row],[amount]]>$Y$7),"Outlier","Normal") -> Normal | P22: =IF(OR(Table1_17[[#This Row],[missing_flag]]="Missing",Table1_17[[#This Row],[outlier_flag]]="Outliers"),"Review","Valid") -> Valid
A23: TRX100021 | B23: 44726 | C23: -2000 | D23: Expense | E23: Rent | F23: Online | G23: West | I23: VEND1022 | J23: Side Official Leave Seem Financial. | K23: Valid | L23: Valid | M23: Valid | N23: =IF(OR(B23="",C23="",D23="",F23=""),"Missing","OK") -> OK | O23: =IF(OR(Table1_17[[#This Row],[amount]]<$Y$8,Table1_17[[#This Row],[amount]]>$Y$7),"Outlier","Normal") -> Normal | P23: =IF(OR(Table1_17[[#This Row],[missing_flag]]="Missing",Table1_17[[#This Row],[outlier_flag]]="Outliers"),"Review","Valid") -> Valid
A24: TRX100022 | B24: 44998 | C24: 203374.65 | D24: Revenue | E24: Service | F24: Online | G24: South | H24: CUST10021 | J24: Must Require Bit Relate Congress Local Improve Organization. | K24: Valid | L24: Valid | M24: Valid | N24: =IF(OR(B24="",C24="",D24="",F24=""),"Missing","OK") -> OK | O24: =IF(OR(Table1_17[[#This Row],[amount]]<$Y$8,Table1_17[[#This Row],[amount]]>$Y$7),"Outlier","Normal") -> Normal | P24: =IF(OR(Table1_17[[#This Row],[missing_flag]]="Missing",Table1_17[[#This Row],[outlier_flag]]="Outliers"),"Review","Valid") -> Valid
A25: TRX100023 | B25: 45189 | C25: 171433.19 | D25: Revenue | E25: Product | F25: Enterprise | G25: West | H25: CUST10218 | J25: Identify Loss Across Fact Government Sea Upon. | K25: Valid | L25: Valid | M25: Valid | N25: =IF(OR(B25="",C25="",D25="",F25=""),"Missing","OK") -> OK | O25: =IF(OR(Table1_17[[#This Row],[amount]]<$Y$8,Table1_17[[#This Row],[amount]]>$Y$7),"Outlier","Normal") -> Normal | P25: =IF(OR(Table1_17[[#This Row],[missing_flag]]="Missing",Table1_17[[#This Row],[outlier_flag]]="Outliers"),"Review","Valid") -> Valid
A26: TRX100024 | B26: 44850 | C26: -60198.87 | D26: Expense | E26: Payroll | F26: Enterprise | G26: North | I26: VEND1058 | J26: Big Fine Cause Full Reality Heart Condition Another. | K26: Valid | L26: Valid | M26: Valid | N26: =IF(OR(B26="",C26="",D26="",F26=""),"Missing","OK") -> OK | O26: =IF(OR(Table1_17[[#This Row],[amount]]<$Y$8,Table1_17[[#This Row],[amount]]>$Y$7),"Outlier","Normal") -> Normal | P26: =IF(OR(Table1_17[[#This Row],[missing_flag]]="Missing",Table1_17[[#This Row],[outlier_flag]]="Outliers"),"Review","Valid") -> Valid
A27: TRX100025 | B27: 45097 | C27: -40143.88 | D27: Expense | E27: Rent | F27: Retail | G27: West | I27: VEND1037 | J27: Good Owner Financial Any Result Summer Physical. | K27: Valid | L27: Valid | M27: Valid | N27: =IF(OR(B27="",C27="",D27="",F27=""),"Missing","OK") -> OK | O27: =IF(OR(Table1_17[[#This Row],[amount]]<$Y$8,Table1_17[[#This Row],[amount]]>$Y$7),"Outlier","Normal") -> Normal | P27: =IF(OR(Table1_17[[#This Row],[missing_flag]]="Missing",Table1_17[[#This Row],[outlier_flag]]="Outliers"),"Review","Valid") -> Valid
A28: TRX100026 | B28: 45208 | C28: -38329 | D28: Expense | E28: Marketing | F28: Enterprise | G28: West | I28: VEND1049 | J28: Sport Note Decide Who Modern Car Knowledge. | K28: Valid | L28: Valid | M28: Valid | N28: =IF(OR(B28="",C28="",D28="",F28=""),"Missing","OK") -> OK | O28: =IF(OR(Table1_17[[#This Row],[amount]]<$Y$8,Table1_17[[#This Row],[amount]]>$Y$7),"Outlier","Normal") -> Normal | P28: =IF(OR(Table1_17[[#This Row],[missing_flag]]="Missing",Table1_17[[#This Row],[outlier_flag]]="Outliers"),"Review","Valid") -> Valid
A29: TRX100027 | B29: 44901 | C29: 193475.45 | D29: Revenue | E29: Service | F29: Retail | G29: South | H29: CUST10146 | J29: Game Step Assume Late Home Order Morning To. | K29: Valid | L29: Valid | M29: Valid | N29: =IF(OR(B29="",C29="",D29="",F29=""),"Missing","OK") -> OK | O29: =IF(OR(Table1_17[[#This Row],[amount]]<$Y$8,Table1_17[[#This Row],[amount]]>$Y$7),"Outlier","Normal") -> Normal | P29: =IF(OR(Table1_17[[#This Row],[missing_flag]]="Missing",Table1_17[[#This Row],[outlier_flag]]="Outliers"),"Review","Valid") -> Valid
A30: TRX100028 | B30: 45002 | C30: 139672.98 | D30: Revenue | E30: Subscription | F30: Enterprise | G30: South | H30: CUST10074 | J30: Nature Need Environment Operation Country Easy Across Choice. | K30: Valid | L30: Valid | M30: Valid | N30: =IF(OR(B30="",C30="",D30="",F30=""),"Missing","OK") -> OK | O30: =IF(OR(Table1_17[[#This Row],[amount]]<$Y$8,Table1_17[[#This Row],[amount]]>$Y$7),"Outlier","Normal") -> Normal | P30: =IF(OR(Table1_17[[#This Row],[missing_flag]]="Missing",Table1_17[[#This Row],[outlier_flag]]="Outliers"),"Review","Valid") -> Valid
A31: TRX100029 | B31: 45188 | C31: 198385.78 | D31: Revenue | E31: Subscription | F31: Enterprise | G31: North | H31: CUST10011 | J31: Scientist Particularly Include True Listen Happy. | K31: Valid | L31: Valid | M31: Valid | N31: =IF(OR(B31="",C31="",D31="",F31=""),"Missing","OK") -> OK | O31: =IF(OR(Table1_17[[#This Row],[amount]]<$Y$8,Table1_17[[#This Row],[amount]]>$Y$7),"Outlier","Normal") -> Normal | P31: =IF(OR(Table1_17[[#This Row],[missing_flag]]="Missing",Table1_17[[#This Row],[outlier_flag]]="Outliers"),"Review","Valid") -> Valid
A32: TRX100030 | B32: 44814 | C32: 137108.16 | D32: Revenue | E32: Service | F32: Enterprise | G32: East | H32: CUST10325 | J32: Citizen Help Never Simple Course. | K32: Valid | L32: Valid | M32: Valid | N32: =IF(OR(B32="",C32="",D32="",F32=""),"Missing","OK") -> OK | O32: =IF(OR(Table1_17[[#This Row],[amount]]<$Y$8,Table1_17[[#This Row],[amount]]>$Y$7),"Outlier","Normal") -> Normal | P32: =IF(OR(Table1_17[[#This Row],[missing_flag]]="Missing",Table1_17[[#This Row],[outlier_flag]]="Outliers"),"Review","Valid") -> Valid
A33: TRX100031 | B33: 44624 | C33: -44326.21 | D33: Expense | E33: Other | F33: Retail | G33: East | I33: VEND1053 | J33: Billion Newspaper Modern Fine Career Somebody. | K33: Valid | L33: Valid | M33: Valid | N33: =IF(OR(B33="",C33="",D33="",F33=""),"Missing","OK") -> OK | O33: =IF(OR(Table1_17[[#This Row],[amount]]<$Y$8,Table1_17[[#This Row],[amount]]>$Y$7),"Outlier","Normal") -> Normal | P33: =IF(OR(Table1_17[[#This Row],[missing_flag]]="Missing",Table1_17[[#This Row],[outlier_flag]]="Outliers"),"Review","Valid") -> Valid
A34: TRX100032 | B34: 44970 | C34: 162088.99 | D34: Revenue | E34: Service | F34: Enterprise | G34: North | H34: CUST10203 | J34: Wall Campaign Might Anyone. | K34: Valid | L34: Valid | M34: Valid | N34: =IF(OR(B34="",C34="",D34="",F34=""),"Missing","OK") -> OK | O34: =IF(OR(Table1_17[[#This Row],[amount]]<$Y$8,Table1_17[[#This Row],[amount]]>$Y$7),"Outlier","Normal") -> Normal | P34: =IF(OR(Table1_17[[#This Row],[missing_flag]]="Missing",Table1_17[[#This Row],[outlier_flag]]="Outliers"),"Review","Valid") -> Valid
A35: TRX100033 | B35: 44847 | C35: 138103.68 | D35: Revenue | E35: Subscription | F35: Online | G35: North | H35: CUST10151 | J35: Could Impact Decide Key. | K35: Valid | L35: Valid | M35: Valid | N35: =IF(OR(B35="",C35="",D35="",F35=""),"Missing","OK") -> OK | O35: =IF(OR(Table1_17[[#This Row],[amount]]<$Y$8,Table1_17[[#This Row],[amount]]>$Y$7),"Outlier","Normal") -> Normal | P35: =IF(OR(Table1_17[[#This Row],[missing_flag]]="Missing",Table1_17[[#This Row],[outlier_flag]]="Outliers"),"Review","Valid") -> Valid
A36: TRX100034 | B36: 44695 | C36: -10197.61 | D36: Expense | E36: Utilities | F36: Retail | G36: East | I36: VEND1014 | J36: Imagine Must Who Discover Since Painting. | K36: Valid | L36: Valid | M36: Valid | N36: =IF(OR(B36="",C36="",D36="",F36=""),"Missing","OK") -> OK | O36: =IF(OR(Table1_17[[#This Row],[amount]]<$Y$8,Table1_17[[#This Row],[amount]]>$Y$7),"Outlier","Normal") -> Normal | P36: =IF(OR(Table1_17[[#This Row],[missing_flag]]="Missing",Table1_17[[#This Row],[outlier_flag]]="Outliers"),"Review","Valid") -> Valid
A37: TRX100035 | B37: 45145 | C37: -62926.94 | D37: Expense | E37: Marketing | F37: Retail | G37: West | I37: VEND1093 | J37: Training Nor Arrive. | K37: Valid | L37: Valid | M37: Valid | N37: =IF(OR(B37="",C37="",D37="",F37=""),"Missing","OK") -> OK | O37: =IF(OR(Table1_17[[#This Row],[amount]]<$Y$8,Table1_17[[#This Row],[amount]]>$Y$7),"Outlier","Normal") -> Normal | P37: =IF(OR(Table1_17[[#This Row],[missing_flag]]="Missing",Table1_17[[#This Row],[outlier_flag]]="Outliers"),"Review","Valid") -> Valid
A38: TRX100036 | B38: 45195 | C38: 144593.87 | D38: Revenue | E38: Service | F38: Enterprise | G38: East | H38: CUST10086 | J38: Field Some Arrive Society Everybody Guy Public. | K38: Valid | L38: Valid | M38: Valid | N38: =IF(OR(B38="",C38="",D38="",F38=""),"Missing","OK") -> OK | O38: =IF(OR(Table1_17[[#This Row],[amount]]<$Y$8,Table1_17[[#This Row],[amount]]>$Y$7),"Outlier","Normal") -> Normal | P38: =IF(OR(Table1_17[[#This Row],[missing_flag]]="Missing",Table1_17[[#This Row],[outlier_flag]]="Outliers"),"Review","Valid") -> Valid
A39: TRX100037 | B39: 44595 | C39: 38814.58 | D39: Revenue | E39: Product | F39: Retail | G39: North | H39: CUST10013 | J39: Order Agreement Mind Everything. | K39: Valid | L39: Valid | M39: Valid | N39: =IF(OR(B39="",C39="",D39="",F39=""),"Missing","OK") -> OK | O39: =IF(OR(Table1_17[[#This Row],[amount]]<$Y$8,Table1_17[[#This Row],[amount]]>$Y$7),"Outlier","Normal") -> Normal | P39: =IF(OR(Table1_17[[#This Row],[missing_flag]]="Missing",Table1_17[[#This Row],[outlier_flag]]="Outliers"),"Review","Valid") -> Valid
A40: TRX100038 | B40: 44983 | C40: -36977.97 | D40: Expense | E40: Rent | F40: Online | G40: East | I40: VEND1082 | J40: Watch Would Miss Interview Water Trouble. | K40: Valid | L40: Valid | M40: Valid | N40: =IF(OR(B40="",C40="",D40="",F40=""),"Missing","OK") -> OK | O40: =IF(OR(Table1_17[[#This Row],[amount]]<$Y$8,Table1_17[[#This Row],[amount]]>$Y$7),"Outlier","Normal") -> Normal | P40: =IF(OR(Table1_17[[#This Row],[missing_flag]]="Missing",Table1_17[[#This Row],[outlier_flag]]="Outliers"),"Review","Valid") -> Valid
A41: TRX100039 | B41: 44914 | C41: -18304.84 | D41: Expense | E41: Payroll | F41: Enterprise | G41: East | I41: VEND1106 | J41: Save In Thing Model. | K41: Valid | L41: Valid | M41: Valid | N41: =IF(OR(B41="",C41="",D41="",F41=""),"Missing","OK") -> OK | O41: =IF(OR(Table1_17[[#This Row],[amount]]<$Y$8,Table1_17[[#This Row],[amount]]>$Y$7),"Outlier","Normal") -> Normal | P41: =IF(OR(Table1_17[[#This Row],[missing_flag]]="Missing",Table1_17[[#This Row],[outlier_flag]]="Outliers"),"Review","Valid") -> Valid
A42: TRX100040 | B42: 45228 | C42: 248459.88 | D42: Revenue | E42: Subscription | F42: Online | G42: East | H42: CUST10022 | J42: Defense Argue Help Someone Action Throw. | K42: Valid | L42: Valid | M42: Valid | N42: =IF(OR(B42="",C42="",D42="",F42=""),"Missing","OK") -> OK | O42: =IF(OR(Table1_17[[#This Row],[amount]]<$Y$8,Table1_17[[#This Row],[amount]]>$Y$7),"Outlier","Normal") -> Normal | P42: =IF(OR(Table1_17[[#This Row],[missing_flag]]="Missing",Table1_17[[#This Row],[outlier_flag]]="Outliers"),"Review","Valid") -> Valid
A43: TRX100041 | B43: 44838 | C43: 120099.72 | D43: Revenue | E43: Product | F43: Online | G43: East | H43: CUST10128 | J43: Reduce Suddenly Against Ball Medical. | K43: Valid | L43: Valid | M43: Valid | N43: =IF(OR(B43="",C43="",D43="",F43=""),"Missing","OK") -> OK | O43: =IF(OR(Table1_17[[#This Row],[amount]]<$Y$8,Table1_17[[#This Row],[amount]]>$Y$7),"Outlier","Normal") -> Normal | P43: =IF(OR(Table1_17[[#This Row],[missing_flag]]="Missing",Table1_17[[#This Row],[outlier_flag]]="Outliers"),"Review","Valid") -> Valid
A44: TRX100042 | B44: 44888 | C44: -39571.02 | D44: Expense | E44: Other | F44: Online | G44: South | I44: VEND1063 | J44: Far Make Skill Lose Audience Art. | K44: Valid | L44: Valid | M44: Valid | N44: =IF(OR(B44="",C44="",D44="",F44=""),"Missing","OK") -> OK | O44: =IF(OR(Table1_17[[#This Row],[amount]]<$Y$8,Table1_17[[#This Row],[amount]]>$Y$7),"Outlier","Normal") -> Normal | P44: =IF(OR(Table1_17[[#This Row],[missing_flag]]="Missing",Table1_17[[#This Row],[outlier_flag]]="Outliers"),"Review","Valid") -> Valid
A45: TRX100043 | B45: 45033 | C45: 79909.54 | D45: Revenue | E45: Subscription | F45: Retail | G45: East | H45: CUST10251 | J45: Tax North Line It Fund Describe. | K45: Valid | L45: Valid | M45: Valid | N45: =IF(OR(B45="",C45="",D45="",F45=""),"Missing","OK") -> OK | O45: =IF(OR(Table1_17[[#This Row],[amount]]<$Y$8,Table1_17[[#This Row],[amount]]>$Y$7),"Outlier","Normal") -> Normal | P45: =IF(OR(Table1_17[[#This Row],[missing_flag]]="Missing",Table1_17[[#This Row],[outlier_flag]]="Outliers"),"Review","Valid") -> Valid
A46: TRX100044 | B46: 44977 | C46: -50444.36 | D46: Expense | E46: Other | F46: Enterprise | G46: North | I46: VEND1020 | J46: Follow Put Campaign Lose Summer Lot If Others. | K46: Valid | L46: Valid | M46: Valid | N46: =IF(OR(B46="",C46="",D46="",F46=""),"Missing","OK") -> OK | O46: =IF(OR(Table1_17[[#This Row],[amount]]<$Y$8,Table1_17[[#This Row],[amount]]>$Y$7),"Outlier","Normal") -> Normal | P46: =IF(OR(Table1_17[[#This Row],[missing_flag]]="Missing",Table1_17[[#This Row],[outlier_flag]]="Outliers"),"Review","Valid") -> Valid
A47: TRX100045 | B47: 44879 | C47: -22716.39 | D47: Expense | E47: Supplies | F47: Retail | G47: East | I47: VEND1062 | J47: Structure Have Effect. | K47: Valid | L47: Valid | M47: Valid | N47: =IF(OR(B47="",C47="",D47="",F47=""),"Missing","OK") -> OK | O47: =IF(OR(Table1_17[[#This Row],[amount]]<$Y$8,Table1_17[[#This Row],[amount]]>$Y$7),"Outlier","Normal") -> Normal | P47: =IF(OR(Table1_17[[#This Row],[missing_flag]]="Missing",Table1_17[[#This Row],[outlier_flag]]="Outliers"),"Review","Valid") -> Valid
A48: TRX100046 | B48: 44934 | C48: -14936.32 | D48: Expense | E48: Marketing | F48: Online | G48: East | I48: VEND1025 | J48: Second Get Its Since Return. | K48: Valid | L48: Valid | M48: Valid | N48: =IF(OR(B48="",C48="",D48="",F48=""),"Missing","OK") -> OK | O48: =IF(OR(Table1_17[[#This Row],[amount]]<$Y$8,Table1_17[[#This Row],[amount]]>$Y$7),"Outlier","Normal") -> Normal | P48: =IF(OR(Table1_17[[#This Row],[missing_flag]]="Missing",Table1_17[[#This Row],[outlier_flag]]="Outliers"),"Review","Valid") -> Valid
A49: TRX100047 | B49: 45199 | C49: 141946.92 | D49: Revenue | E49: Service | F49: Retail | G49: West | H49: CUST10342 | J49: Then Section Each Support Majority. | K49: Valid | L49: Valid | M49: Valid | N49: =IF(OR(B49="",C49="",D49="",F49=""),"Missing","OK") -> OK | O49: =IF(OR(Table1_17[[#This Row],[amount]]<$Y$8,Table1_17[[#This Row],[amount]]>$Y$7),"Outlier","Normal") -> Normal | P49: =IF(OR(Table1_17[[#This Row],[missing_flag]]="Missing",Table1_17[[#This Row],[outlier_flag]]="Outliers"),"Review","Valid") -> Valid
A50: TRX100048 | B50: 45265 | C50: -28844.76 | D50: Expense | E50: Supplies | F50: Online | G50: West | I50: VEND1060 | J50: Where Keep Leader Computer Father Brother A Give. | K50: Valid | L50: Valid | M50: Valid | N50: =IF(OR(B50="",C50="",D50="",F50=""),"Missing","OK") -> OK | O50: =IF(OR(Table1_17[[#This Row],[amount]]<$Y$8,Table1_17[[#This Row],[amount]]>$Y$7),"Outlier","Normal") -> Normal | P50: =IF(OR(Table1_17[[#This Row],[missing_flag]]="Missing",Table1_17[[#This Row],[outlier_flag]]="Outliers"),"Review","Valid") -> Valid
A51: TRX100049 | B51: 44782 | C51: -66244 | D51: Expense | E51: Supplies | F51: Enterprise | G51: North | I51: VEND1089 | J51: Big Itself Serious. | K51: Valid | L51: Valid | M51: Valid | N51: =IF(OR(B51="",C51="",D51="",F51=""),"Missing","OK") -> OK | O51: =IF(OR(Table1_17[[#This Row],[amount]]<$Y$8,Table1_17[[#This Row],[amount]]>$Y$7),"Outlier","Normal") -> Normal | P51: =IF(OR(Table1_17[[#This Row],[missing_flag]]="Missing",Table1_17[[#This Row],[outlier_flag]]="Outliers"),"Review","Valid") -> Valid
A52: TRX100050 | B52: 45018 | C52: 15704.88 | D52: Asset | E52: Asset | F52: Enterprise | G52: East | J52: Test Fill Perform Voice. | K52: Valid | L52: Valid | M52: Valid | N52: =IF(OR(B52="",C52="",D52="",F52=""),"Missing","OK") -> OK | O52: =IF(OR(Table1_17[[#This Row],[amount]]<$Y$8,Table1_17[[#This Row],[amount]]>$Y$7),"Outlier","Normal") -> Normal | P52: =IF(OR(Table1_17[[#This Row],[missing_flag]]="Missing",Table1_17[[#This Row],[outlier_flag]]="Outliers"),"Review","Valid") -> Valid
A53: TRX100051 | B53: 44822 | C53: 209846.71 | D53: Revenue | E53: Subscription | F53: Retail | G53: South | H53: CUST10190 | J53: School Common Voice Itself. | K53: Valid | L53: Valid | M53: Valid | N53: =IF(OR(B53="",C53="",D53="",F53=""),"Missing","OK") -> OK | O53: =IF(OR(Table1_17[[#This Row],[amount]]<$Y$8,Table1_17[[#This Row],[amount]]>$Y$7),"Outlier","Normal") -> Normal | P53: =IF(OR(Table1_17[[#This Row],[missing_flag]]="Missing",Table1_17[[#This Row],[outlier_flag]]="Outliers"),"Review","Valid") -> Valid
A54: TRX100052 | B54: 44728 | C54: -45798.81 | D54: Expense | E54: Marketing | F54: Enterprise | G54: East | I54: VEND1011 | J54: Majority Early Special Record Sit Scene Price. | K54: Valid | L54: Valid | M54: Valid | N54: =IF(OR(B54="",C54="",D54="",F54=""),"Missing","OK") -> OK | O54: =IF(OR(Table1_17[[#This Row],[amount]]<$Y$8,Table1_17[[#This Row],[amount]]>$Y$7),"Outlier","Normal") -> Normal | P54: =IF(OR(Table1_17[[#This Row],[missing_flag]]="Missing",Table1_17[[#This Row],[outlier_flag]]="Outliers"),"Review","Valid") -> Valid
A55: TRX100053 | B55: 44687 | C55: -22712.23 | D55: Expense | E55: Payroll | F55: Enterprise | G55: North | I55: VEND1079 | J55: Daughter Training Suffer Miss Money. | K55: Valid | L55: Valid | M55: Valid | N55: =IF(OR(B55="",C55="",D55="",F55=""),"Missing","OK") -> OK | O55: =IF(OR(Table1_17[[#This Row],[amount]]<$Y$8,Table1_17[[#This Row],[amount]]>$Y$7),"Outlier","Normal") -> Normal | P55: =IF(OR(Table1_17[[#This Row],[missing_flag]]="Missing",Table1_17[[#This Row],[outlier_flag]]="Outliers"),"Review","Valid") -> Valid
A56: TRX100054 | B56: 44881 | C56: -51925.51 | D56: Expense | E56: Other | F56: Online | G56: East | I56: VEND1098 | J56: Including Measure Leave Road Leg Mention. | K56: Valid | L56: Valid | M56: Valid | N56: =IF(OR(B56="",C56="",D56="",F56=""),"Missing","OK") -> OK | O56: =IF(OR(Table1_17[[#This Row],[amount]]<$Y$8,Table1_17[[#This Row],[amount]]>$Y$7),"Outlier","Normal") -> Normal | P56: =IF(OR(Table1_17[[#This Row],[missing_flag]]="Missing",Table1_17[[#This Row],[outlier_flag]]="Outliers"),"Review","Valid") -> Valid
A57: TRX100055 | B57: 44960 | C57: -42768.16 | D57: Expense | E57: Rent | F57: Online | G57: North | I57: VEND1082 | J57: Technology Far Reach Thought Probably Cover Increase. | K57: Valid | L57: Valid | M57: Valid | N57: =IF(OR(B57="",C57="",D57="",F57=""),"Missing","OK") -> OK | O57: =IF(OR(Table1_17[[#This Row],[amount]]<$Y$8,Table1_17[[#This Row],[amount]]>$Y$7),"Outlier","Normal") -> Normal | P57: =IF(OR(Table1_17[[#This Row],[missing_flag]]="Missing",Table1_17[[#This Row],[outlier_flag]]="Outliers"),"Review","Valid") -> Valid
A58: TRX100056 | B58: 44655 | C58: -22339.95 | D58: Expense | E58: Marketing | F58: Retail | G58: East | I58: VEND1001 | J58: Play Prepare Red Goal. | K58: Valid | L58: Valid | M58: Valid | N58: =IF(OR(B58="",C58="",D58="",F58=""),"Missing","OK") -> OK | O58: =IF(OR(Table1_17[[#This Row],[amount]]<$Y$8,Table1_17[[#This Row],[amount]]>$Y$7),"Outlier","Normal") -> Normal | P58: =IF(OR(Table1_17[[#This Row],[missing_flag]]="Missing",Table1_17[[#This Row],[outlier_flag]]="Outliers"),"Review","Valid") -> Valid
A59: TRX100057 | B59: 44995 | C59: -43856.82 | D59: Expense | E59: Utilities | F59: Enterprise | G59: West | I59: VEND1042 | J59: Hard This Despite Certain They Both Provide Machine. | K59: Valid | L59: Valid | M59: Valid | N59: =IF(OR(B59="",C59="",D59="",F59=""),"Missing","OK") -> OK | O59: =IF(OR(Table1_17[[#This Row],[amount]]<$Y$8,Table1_17[[#This Row],[amount]]>$Y$7),"Outlier","Normal") -> Normal | P59: =IF(OR(Table1_17[[#This Row],[missing_flag]]="Missing",Table1_17[[#This Row],[outlier_flag]]="Outliers"),"Review","Valid") -> Valid
A60: TRX100058 | B60: 44730 | C60: 86224.06 | D60: Revenue | E60: Product | F60: Retail | G60: East | H60: CUST10151 | J60: Summer Everyone His Magazine Six Value Week. | K60: Valid | L60: Valid | M60: Valid | N60: =IF(OR(B60="",C60="",D60="",F60=""),"Missing","OK") -> OK | O60: =IF(OR(Table1_17[[#This Row],[amount]]<$Y$8,Table1_17[[#This Row],[amount]]>$Y$7),"Outlier","Normal") -> Normal | P60: =IF(OR(Table1_17[[#This Row],[missing_flag]]="Missing",Table1_17[[#This Row],[outlier_flag]]="Outliers"),"Review","Valid") -> Valid
A61: TRX100059 | B61: 44818 | C61: 196305.77 | D61: Revenue | E61: Service | F61: Enterprise | G61: West | H61: CUST10016 | J61: Pm Like Matter Price Personal For. | K61: Valid | L61: Valid | M61: Valid | N61: =IF(OR(B61="",C61="",D61="",F61=""),"Missing","OK") -> OK | O61: =IF(OR(Table1_17[[#This Row],[amount]]<$Y$8,Table1_17[[#This Row],[amount]]>$Y$7),"Outlier","Normal") -> Normal | P61: =IF(OR(Table1_17[[#This Row],[missing_flag]]="Missing",Table1_17[[#This Row],[outlier_flag]]="Outliers"),"Review","Valid") -> Valid
A62: TRX100060 | B62: 45271 | C62: 144148.9 | D62: Revenue | E62: Product | F62: Online | G62: South | H62: CUST10049 | J62: True Shoulder Away. | K62: Valid | L62: Valid | M62: Valid | N62: =IF(OR(B62="",C62="",D62="",F62=""),"Missing","OK") -> OK | O62: =IF(OR(Table1_17[[#This Row],[amount]]<$Y$8,Table1_17[[#This Row],[amount]]>$Y$7),"Outlier","Normal") -> Normal | P62: =IF(OR(Table1_17[[#This Row],[missing_flag]]="Missing",Table1_17[[#This Row],[outlier_flag]]="Outliers"),"Review","Valid") -> Valid
A63: TRX100061 | B63: 44872 | C63: 161193.89 | D63: Revenue | E63: Product | F63: Online | G63: South | H63: CUST10129 | J63: Page Truth Although Under For Water Analysis. | K63: Valid | L63: Valid | M63: Valid | N63: =IF(OR(B63="",C63="",D63="",F63=""),"Missing","OK") -> OK | O63: =IF(OR(Table1_17[[#This Row],[amount]]<$Y$8,Table1_17[[#This Row],[amount]]>$Y$7),"Outlier","Normal") -> Normal | P63: =IF(OR(Table1_17[[#This Row],[missing_flag]]="Missing",Table1_17[[#This Row],[outlier_flag]]="Outliers"),"Review","Valid") -> Valid
A64: TRX100062 | B64: 44808 | C64: 157413.67 | D64: Revenue | E64: Service | F64: Online | G64: West | H64: CUST10183 | J64: Early Choice Speech Follow Fund Measure. | K64: Valid | L64: Valid | M64: Valid | N64: =IF(OR(B64="",C64="",D64="",F64=""),"Missing","OK") -> OK | O64: =IF(OR(Table1_17[[#This Row],[amount]]<$Y$8,Table1_17[[#This Row],[amount]]>$Y$7),"Outlier","Normal") -> Normal | P64: =IF(OR(Table1_17[[#This Row],[missing_flag]]="Missing",Table1_17[[#This Row],[outlier_flag]]="Outliers"),"Review","Valid") -> Valid
A65: TRX100063 | B65: 44583 | C65: 113690.25 | D65: Revenue | E65: Subscription | F65: Enterprise | G65: West | H65: CUST10348 | J65: Same Whether Interesting Half Republican. | K65: Valid | L65: Valid | M65: Valid | N65: =IF(OR(B65="",C65="",D65="",F65=""),"Missing","OK") -> OK | O65: =IF(OR(Table1_17[[#This Row],[amount]]<$Y$8,Table1_17[[#This Row],[amount]]>$Y$7),"Outlier","Normal") -> Normal | P65: =IF(OR(Table1_17[[#This Row],[missing_flag]]="Missing",Table1_17[[#This Row],[outlier_flag]]="Outliers"),"Review","Valid") -> Valid
A66: TRX100064 | B66: 45152 | C66: 194267.47 | D66: Revenue | E66: Subscription | F66: Online | G66: East | H66: CUST10075 | J66: Half Toward His. | K66: Valid | L66: Valid | M66: Valid | N66: =IF(OR(B66="",C66="",D66="",F66=""),"Missing","OK") -> OK | O66: =IF(OR(Table1_17[[#This Row],[amount]]<$Y$8,Table1_17[[#This Row],[amount]]>$Y$7),"Outlier","Normal") -> Normal | P66: =IF(OR(Table1_17[[#This Row],[missing_flag]]="Missing",Table1_17[[#This Row],[outlier_flag]]="Outliers"),"Review","Valid") -> Valid
A67: TRX100065 | B67: 45018 | C67: -53590.9 | D67: Expense | E67: Marketing | F67: Enterprise | G67: South | I67: VEND1107 | J67: Source Learn Expect Show. | K67: Valid | L67: Valid | M67: Valid | N67: =IF(OR(B67="",C67="",D67="",F67=""),"Missing","OK") -> OK | O67: =IF(OR(Table1_17[[#This Row],[amount]]<$Y$8,Table1_17[[#This Row],[amount]]>$Y$7),"Outlier","Normal") -> Normal | P67: =IF(OR(Table1_17[[#This Row],[missing_flag]]="Missing",Table1_17[[#This Row],[outlier_flag]]="Outliers"),"Review","Valid") -> Valid
A68: TRX100066 | B68: 44844 | C68: -29061.06 | D68: Expense | E68: Other | F68: Retail | G68: North | I68: VEND1019 | J68: House Performance Sign Deep. | K68: Valid | L68: Valid | M68: Valid | N68: =IF(OR(B68="",C68="",D68="",F68=""),"Missing","OK") -> OK | O68: =IF(OR(Table1_17[[#This Row],[amount]]<$Y$8,Table1_17[[#This Row],[amount]]>$Y$7),"Outlier","Normal") -> Normal | P68: =IF(OR(Table1_17[[#This Row],[missing_flag]]="Missing",Table1_17[[#This Row],[outlier_flag]]="Outliers"),"Review","Valid") -> Valid
A69: TRX100067 | B69: 44904 | C69: -48080.35 | D69: Expense | E69: Rent | F69: Retail | G69: North | I69: VEND1030 | J69: Home Now Local Perform By. | K69: Valid | L69: Valid | M69: Valid | N69: =IF(OR(B69="",C69="",D69="",F69=""),"Missing","OK") -> OK | O69: =IF(OR(Table1_17[[#This Row],[amount]]<$Y$8,Table1_17[[#This Row],[amount]]>$Y$7),"Outlier","Normal") -> Normal | P69: =IF(OR(Table1_17[[#This Row],[missing_flag]]="Missing",Table1_17[[#This Row],[outlier_flag]]="Outliers"),"Review","Valid") -> Valid
A70: TRX100068 | B70: 44749 | C70: 218024.69 | D70: Revenue | E70: Product | F70: Online | G70: North | H70: CUST10321 | J70: Dog Eight Perhaps Audience Past Eye. | K70: Valid | L70: Valid | M70: Valid | N70: =IF(OR(B70="",C70="",D70="",F70=""),"Missing","OK") -> OK | O70: =IF(OR(Table1_17[[#This Row],[amount]]<$Y$8,Table1_17[[#This Row],[amount]]>$Y$7),"Outlier","Normal") -> Normal | P70: =IF(OR(Table1_17[[#This Row],[missing_flag]]="Missing",Table1_17[[#This Row],[outlier_flag]]="Outliers"),"Review","Valid") -> Valid
A71: TRX100069 | B71: 44749 | C71: -38127.82 | D71: Expense | E71: Rent | F71: Enterprise | G71: West | I71: VEND1086 | J71: His Another Government Threat Choose Water Fear. | K71: Valid | L71: Valid | M71: Valid | N71: =IF(OR(B71="",C71="",D71="",F71=""),"Missing","OK") -> OK | O71: =IF(OR(Table1_17[[#This Row],[amount]]<$Y$8,Table1_17[[#This Row],[amount]]>$Y$7),"Outlier","Normal") -> Normal | P71: =IF(OR(Table1_17[[#This Row],[missing_flag]]="Missing",Table1_17[[#This Row],[outlier_flag]]="Outliers"),"Review","Valid") -> Valid
A72: TRX100070 | B72: 44989 | C72: -31873.97 | D72: Expense | E72: Rent | F72: Retail | G72: North | I72: VEND1086 | J72: Enjoy Keep Pass Write State Even Bank. | K72: Valid | L72: Valid | M72: Valid | N72: =IF(OR(B72="",C72="",D72="",F72=""),"Missing","OK") -> OK | O72: =IF(OR(Table1_17[[#This Row],[amount]]<$Y$8,Table1_17[[#This Row],[amount]]>$Y$7),"Outlier","Normal") -> Normal | P72: =IF(OR(Table1_17[[#This Row],[missing_flag]]="Missing",Table1_17[[#This Row],[outlier_flag]]="Outliers"),"Review","Valid") -> Valid
A73: TRX100071 | B73: 45082 | C73: 203084.24 | D73: Revenue | E73: Subscription | F73: Online | G73: West | H73: CUST10116 | J73: Possible Talk Model Why We Town Decade. | K73: Valid | L73: Valid | M73: Valid | N73: =IF(OR(B73="",C73="",D73="",F73=""),"Missing","OK") -> OK | O73: =IF(OR(Table1_17[[#This Row],[amount]]<$Y$8,Table1_17[[#This Row],[amount]]>$Y$7),"Outlier","Normal") -> Normal | P73: =IF(OR(Table1_17[[#This Row],[missing_flag]]="Missing",Table1_17[[#This Row],[outlier_flag]]="Outliers"),"Review","Valid") -> Valid
A74: TRX100072 | B74: 45290 | C74: 222948.96 | D74: Revenue | E74: Subscription | F74: Online | G74: North | H74: CUST10063 | J74: Black Sit Anyone Language Song Show Watch Better. | K74: Valid | L74: Valid | M74: Valid | N74: =IF(OR(B74="",C74="",D74="",F74=""),"Missing","OK") -> OK | O74: =IF(OR(Table1_17[[#This Row],[amount]]<$Y$8,Table1_17[[#This Row],[amount]]>$Y$7),"Outlier","Normal") -> Normal | P74: =IF(OR(Table1_17[[#This Row],[missing_flag]]="Missing",Table1_17[[#This Row],[outlier_flag]]="Outliers"),"Review","Valid") -> Valid
A75: TRX100073 | B75: 45270 | C75: 238667.54 | D75: Revenue | E75: Product | F75: Enterprise | G75: South | H75: CUST10137 | J75: Rate Reflect Building Guess Well Tv. | K75: Valid | L75: Valid | M75: Valid | N75: =IF(OR(B75="",C75="",D75="",F75=""),"Missing","OK") -> OK | O75: =IF(OR(Table1_17[[#This Row],[amount]]<$Y$8,Table1_17[[#This Row],[amount]]>$Y$7),"Outlier","Normal") -> Normal | P75: =IF(OR(Table1_17[[#This Row],[missing_flag]]="Missing",Table1_17[[#This Row],[outlier_flag]]="Outliers"),"Review","Valid") -> Valid
A76: TRX100074 | B76: 44673 | C76: 132774.78 | D76: Revenue | E76: Subscription | F76: Retail | G76: South | H76: CUST10298 | J76: And Stop Raise Somebody Nice. | K76: Valid | L76: Valid | M76: Valid | N76: =IF(OR(B76="",C76="",D76="",F76=""),"Missing","OK") -> OK | O76: =IF(OR(Table1_17[[#This Row],[amount]]<$Y$8,Table1_17[[#This Row],[amount]]>$Y$7),"Outlier","Normal") -> Normal | P76: =IF(OR(Table1_17[[#This Row],[missing_flag]]="Missing",Table1_17[[#This Row],[outlier_flag]]="Outliers"),"Review","Valid") -> Valid
A77: TRX100075 | B77: 45186 | C77: 188545.69 | D77: Revenue | E77: Subscription | F77: Enterprise | G77: North | H77: CUST10187 | J77: Wonder Increase Hundred Today Final Debate. | K77: Valid | L77: Valid | M77: Valid | N77: =IF(OR(B77="",C77="",D77="",F77=""),"Missing","OK") -> OK | O77: =IF(OR(Table1_17[[#This Row],[amount]]<$Y$8,Table1_17[[#This Row],[amount]]>$Y$7),"Outlier","Normal") -> Normal | P77: =IF(OR(Table1_17[[#This Row],[missing_flag]]="Missing",Table1_17[[#This Row],[outlier_flag]]="Outliers"),"Review","Valid") -> Valid
A78: TRX100076 | B78: 45056 | C78: 138240.93 | D78: Revenue | E78: Service | F78: Retail | G78: East | H78: CUST10285 | J78: Pick Fast One Entire. | K78: Valid | L78: Valid | M78: Valid | N78: =IF(OR(B78="",C78="",D78="",F78=""),"Missing","OK") -> OK | O78: =IF(OR(Table1_17[[#This Row],[amount]]<$Y$8,Table1_17[[#This Row],[amount]]>$Y$7),"Outlier","Normal") -> Normal | P78: =IF(OR(Table1_17[[#This Row],[missing_flag]]="Missing",Table1_17[[#This Row],[outlier_flag]]="Outliers"),"Review","Valid") -> Valid
A79: TRX100077 | B79: 45149 | C79: -14341.81 | D79: Expense | E79: Payroll | F79: Online | G79: North | I79: VEND1095 | J79: East Very Manager Set Act Perhaps Company Ability. | K79: Valid | L79: Valid | M79: Valid | N79: =IF(OR(B79="",C79="",D79="",F79=""),"Missing","OK") -> OK | O79: =IF(OR(Table1_17[[#This Row],[amount]]<$Y$8,Table1_17[[#This Row],[amount]]>$Y$7),"Outlier","Normal") -> Normal | P79: =IF(OR(Table1_17[[#This Row],[missing_flag]]="Missing",Table1_17[[#This Row],[outlier_flag]]="Outliers"),"Review","Valid") -> Valid
A80: TRX100078 | B80: 44904 | C80: 163678.6 | D80: Revenue | E80: Product | F80: Enterprise | G80: West | H80: CUST10207 | J80: Three Specific Late Economic Serious Word. | K80: Valid | L80: Valid | M80: Valid | N80: =IF(OR(B80="",C80="",D80="",F80=""),"Missing","OK") -> OK | O80: =IF(OR(Table1_17[[#This Row],[amount]]<$Y$8,Table1_17[[#This Row],[amount]]>$Y$7),"Outlier","Normal") -> Normal | P80: =IF(OR(Table1_17[[#This Row],[missing_flag]]="Missing",Table1_17[[#This Row],[outlier_flag]]="Outliers"),"Review","Valid") -> Valid
A81: TRX100079 | B81: 44851 | C81: 198317.9 | D81: Revenue | E81: Product | F81: Enterprise | G81: West | H81: CUST10207 | J81: Continue Beyond Suffer Plant Student. | K81: Valid | L81: Valid | M81: Valid | N81: =IF(OR(B81="",C81="",D81="",F81=""),"Missing","OK") -> OK | O81: =IF(OR(Table1_17[[#This Row],[amount]]<$Y$8,Table1_17[[#This Row],[amount]]>$Y$7),"Outlier","Normal") -> Normal | P81: =IF(OR(Table1_17[[#This Row],[missing_flag]]="Missing",Table1_17[[#This Row],[outlier_flag]]="Outliers"),"Review","Valid") -> Valid
A82: TRX100080 | B82: 45153 | C82: 188616.88 | D82: Revenue | E82: Product | F82: Retail | G82: North | H82: CUST10108 | J82: Doctor Surface Girl Friend Everybody Thousand Under. | K82: Valid | L82: Valid | M82: Valid | N82: =IF(OR(B82="",C82="",D82="",F82=""),"Missing","OK") -> OK | O82: =IF(OR(Table1_17[[#This Row],[amount]]<$Y$8,Table1_17[[#This Row],[amount]]>$Y$7),"Outlier","Normal") -> Normal | P82: =IF(OR(Table1_17[[#This Row],[missing_flag]]="Missing",Table1_17[[#This Row],[outlier_flag]]="Outliers"),"Review","Valid") -> Valid
A83: TRX100081 | B83: 44738 | C83: -25218.03 | D83: Expense | E83: Marketing | F83: Online | G83: East | I83: VEND1089 | J83: Kid Item Feeling Less Player. | K83: Valid | L83: Valid | M83: Valid | N83: =IF(OR(B83="",C83="",D83="",F83=""),"Missing","OK") -> OK | O83: =IF(OR(Table1_17[[#This Row],[amount]]<$Y$8,Table1_17[[#This Row],[amount]]>$Y$7),"Outlier","Normal") -> Normal | P83: =IF(OR(Table1_17[[#This Row],[missing_flag]]="Missing",Table1_17[[#This Row],[outlier_flag]]="Outliers"),"Review","Valid") -> Valid
A84: TRX100082 | B84: 45196 | C84: -15892.26 | D84: Expense | E84: Supplies | F84: Enterprise | G84: South | I84: VEND1025 | J84: Increase Mouth Your Indeed. | K84: Valid | L84: Valid | M84: Valid | N84: =IF(OR(B84="",C84="",D84="",F84=""),"Missing","OK") -> OK | O84: =IF(OR(Table1_17[[#This Row],[amount]]<$Y$8,Table1_17[[#This Row],[amount]]>$Y$7),"Outlier","Normal") -> Normal | P84: =IF(OR(Table1_17[[#This Row],[missing_flag]]="Missing",Table1_17[[#This Row],[outlier_flag]]="Outliers"),"Review","Valid") -> Valid
A85: TRX100083 | B85: 44807 | C85: 199974.44 | D85: Revenue | E85: Subscription | F85: Enterprise | G85: South | H85: CUST10092 | J85: Letter Along Six Agent Staff Industry Who. | K85: Valid | L85: Valid | M85: Valid | N85: =IF(OR(B85="",C85="",D85="",F85=""),"Missing","OK") -> OK | O85: =IF(OR(Table1_17[[#This Row],[amount]]<$Y$8,Table1_17[[#This Row],[amount]]>$Y$7),"Outlier","Normal") -> Normal | P85: =IF(OR(Table1_17[[#This Row],[missing_flag]]="Missing",Table1_17[[#This Row],[outlier_flag]]="Outliers"),"Review","Valid") -> Valid
A86: TRX100084 | B86: 44686 | C86: 128923.58 | D86: Revenue | E86: Service | F86: Enterprise | G86: North | H86: CUST10082 | J86: Cell Prevent Goal View Water Shake Matter Effect. | K86: Valid | L86: Valid | M86: Valid | N86: =IF(OR(B86="",C86="",D86="",F86=""),"Missing","OK") -> OK | O86: =IF(OR(Table1_17[[#This Row],[amount]]<$Y$8,Table1_17[[#This Row],[amount]]>$Y$7),"Outlier","Normal") -> Normal | P86: =IF(OR(Table1_17[[#This Row],[missing_flag]]="Missing",Table1_17[[#This Row],[outlier_flag]]="Outliers"),"Review","Valid") -> Valid
A87: TRX100085 | B87: 44982 | C87: 67222.23 | D87: Revenue | E87: Service | F87: Online | G87: West | H87: CUST10209 | J87: End Cover A Enough Speak Figure. | K87: Valid | L87: Valid | M87: Valid | N87: =IF(OR(B87="",C87="",D87="",F87=""),"Missing","OK") -> OK | O87: =IF(OR(Table1_17[[#This Row],[amount]]<$Y$8,Table1_17[[#This Row],[amount]]>$Y$7),"Outlier","Normal") -> Normal | P87: =IF(OR(Table1_17[[#This Row],[missing_flag]]="Missing",Table1_17[[#This Row],[outlier_flag]]="Outliers"),"Review","Valid") -> Valid
A88: TRX100086 | B88: 44923 | C88: 186952.56 | D88: Revenue | E88: Subscription | F88: Online | G88: West | H88: CUST10089 | J88: Economic Behind Young American Artist Main Personal. | K88: Valid | L88: Valid | M88: Valid | N88: =IF(OR(B88="",C88="",D88="",F88=""),"Missing","OK") -> OK | O88: =IF(OR(Table1_17[[#This Row],[amount]]<$Y$8,Table1_17[[#This Row],[amount]]>$Y$7),"Outlier","Normal") -> Normal | P88: =IF(OR(Table1_17[[#This Row],[missing_flag]]="Missing",Table1_17[[#This Row],[outlier_flag]]="Outliers"),"Review","Valid") -> Valid
A89: TRX100087 | B89: 45116 | C89: 164462.06 | D89: Revenue | E89: Service | F89: Retail | G89: East | H89: CUST10042 | J89: Girl Reveal Order Deep Chair Cut Sit. | K89: Valid | L89: Valid | M89: Valid | N89: =IF(OR(B89="",C89="",D89="",F89=""),"Missing","OK") -> OK | O89: =IF(OR(Table1_17[[#This Row],[amount]]<$Y$8,Table1_17[[#This Row],[amount]]>$Y$7),"Outlier","Normal") -> Normal | P89: =IF(OR(Table1_17[[#This Row],[missing_flag]]="Missing",Table1_17[[#This Row],[outlier_flag]]="Outliers"),"Review","Valid") -> Valid
A90: TRX100088 | B90: 44872 | C90: 18077.56 | D90: Equity | E90: Equity | F90: Enterprise | G90: South | J90: Once Fact Interest Difference Section Remain. | K90: Valid | L90: Valid | M90: Valid | N90: =IF(OR(B90="",C90="",D90="",F90=""),"Missing","OK") -> OK | O90: =IF(OR(Table1_17[[#This Row],[amount]]<$Y$8,Table1_17[[#This Row],[amount]]>$Y$7),"Outlier","Normal") -> Normal | P90: =IF(OR(Table1_17[[#This Row],[missing_flag]]="Missing",Table1_17[[#This Row],[outlier_flag]]="Outliers"),"Review","Valid") -> Valid
A91: TRX100089 | B91: 45213 | C91: 72337.28 | D91: Revenue | E91: Service | F91: Online | G91: South | H91: CUST10157 | J91: Able Finish They Defense Yet Activity. | K91: Valid | L91: Valid | M91: Valid | N91: =IF(OR(B91="",C91="",D91="",F91=""),"Missing","OK") -> OK | O91: =IF(OR(Table1_17[[#This Row],[amount]]<$Y$8,Table1_17[[#This Row],[amount]]>$Y$7),"Outlier","Normal") -> Normal | P91: =IF(OR(Table1_17[[#This Row],[missing_flag]]="Missing",Table1_17[[#This Row],[outlier_flag]]="Outliers"),"Review","Valid") -> Valid
A92: TRX100090 | B92: 44760 | C92: -40667.5 | D92: Expense | E92: Rent | F92: Online | G92: South | I92: VEND1090 | J92: Instead Age Animal Popular Parent Baby. | K92: Valid | L92: Valid | M92: Valid | N92: =IF(OR(B92="",C92="",D92="",F92=""),"Missing","OK") -> OK | O92: =IF(OR(Table1_17[[#This Row],[amount]]<$Y$8,Table1_17[[#This Row],[amount]]>$Y$7),"Outlier","Normal") -> Normal | P92: =IF(OR(Table1_17[[#This Row],[missing_flag]]="Missing",Table1_17[[#This Row],[outlier_flag]]="Outliers"),"Review","Valid") -> Valid
A93: TRX100091 | B93: 44565 | C93: 177006.22 | D93: Revenue | E93: Product | F93: Retail | G93: West | H93: CUST10212 | J93: Choose Per Range Week. | K93: Valid | L93: Valid | M93: Valid | N93: =IF(OR(B93="",C93="",D93="",F93=""),"Missing","OK") -> OK | O93: =IF(OR(Table1_17[[#This Row],[amount]]<$Y$8,Table1_17[[#This Row],[amount]]>$Y$7),"Outlier","Normal") -> Normal | P93: =IF(OR(Table1_17[[#This Row],[missing_flag]]="Missing",Table1_17[[#This Row],[outlier_flag]]="Outliers"),"Review","Valid") -> Valid
A94: TRX100092 | B94: 44759 | C94: -33821.98 | D94: Expense | E94: Other | F94: Online | G94: West | I94: VEND1059 | J94: Lay Buy Bar Century. | K94: Valid | L94: Valid | M94: Valid | N94: =IF(OR(B94="",C94="",D94="",F94=""),"Missing","OK") -> OK | O94: =IF(OR(Table1_17[[#This Row],[amount]]<$Y$8,Table1_17[[#This Row],[amount]]>$Y$7),"Outlier","Normal") -> Normal | P94: =IF(OR(Table1_17[[#This Row],[missing_flag]]="Missing",Table1_17[[#This Row],[outlier_flag]]="Outliers"),"Review","Valid") -> Valid
A95: TRX100093 | B95: 44749 | C95: 113760.1 | D95: Revenue | E95: Service | F95: Enterprise | G95: South | H95: CUST10232 | J95: Congress Whose Main Matter Coach Loss Executive. | K95: Valid | L95: Valid | M95: Valid | N95: =IF(OR(B95="",C95="",D95="",F95=""),"Missing","OK") -> OK | O95: =IF(OR(Table1_17[[#This Row],[amount]]<$Y$8,Table1_17[[#This Row],[amount]]>$Y$7),"Outlier","Normal") -> Normal | P95: =IF(OR(Table1_17[[#This Row],[missing_flag]]="Missing",Table1_17[[#This Row],[outlier_flag]]="Outliers"),"Review","Valid") -> Valid
A96: TRX100094 | B96: 44618 | C96: 68040.32 | D96: Revenue | E96: Service | F96: Retail | G96: South | H96: CUST10121 | J96: Bar Rock Democratic Positive Live Easy Grow. | K96: Valid | L96: Valid | M96: Valid | N96: =IF(OR(B96="",C96="",D96="",F96=""),"Missing","OK") -> OK | O96: =IF(OR(Table1_17[[#This Row],[amount]]<$Y$8,Table1_17[[#This Row],[amount]]>$Y$7),"Outlier","Normal") -> Normal | P96: =IF(OR(Table1_17[[#This Row],[missing_flag]]="Missing",Table1_17[[#This Row],[outlier_flag]]="Outliers"),"Review","Valid") -> Valid
A97: TRX100095 | B97: 45132 | C97: 114168.76 | D97: Revenue | E97: Product | F97: Retail | G97: West | H97: CUST10237 | J97: Certainly Believe White Money. | K97: Valid | L97: Valid | M97: Valid | N97: =IF(OR(B97="",C97="",D97="",F97=""),"Missing","OK") -> OK | O97: =IF(OR(Table1_17[[#This Row],[amount]]<$Y$8,Table1_17[[#This Row],[amount]]>$Y$7),"Outlier","Normal") -> Normal | P97: =IF(OR(Table1_17[[#This Row],[missing_flag]]="Missing",Table1_17[[#This Row],[outlier_flag]]="Outliers"),"Review","Valid") -> Valid
A98: TRX100096 | B98: 45034 | C98: 104796.05 | D98: Revenue | E98: Product | F98: Online | G98: West | H98: CUST10266 | J98: Support Visit Else Lead Call. | K98: Valid | L98: Valid | M98: Valid | N98: =IF(OR(B98="",C98="",D98="",F98=""),"Missing","OK") -> OK | O98: =IF(OR(Table1_17[[#This Row],[amount]]<$Y$8,Table1_17[[#This Row],[amount]]>$Y$7),"Outlier","Normal") -> Normal | P98: =IF(OR(Table1_17[[#This Row],[missing_flag]]="Missing",Table1_17[[#This Row],[outlier_flag]]="Outliers"),"Review","Valid") -> Valid
A99: TRX100097 | B99: 44637 | C99: -40864.74 | D99: Expense | E99: Other | F99: Retail | G99: East | I99: VEND1072 | J99: But Share Truth Conference Seem Tv. | K99: Valid | L99: Valid | M99: Valid | N99: =IF(OR(B99="",C99="",D99="",F99=""),"Missing","OK") -> OK | O99: =IF(OR(Table1_17[[#This Row],[amount]]<$Y$8,Table1_17[[#This Row],[amount]]>$Y$7),"Outlier","Normal") -> Normal | P99: =IF(OR(Table1_17[[#This Row],[missing_flag]]="Missing",Table1_17[[#This Row],[outlier_flag]]="Outliers"),"Review","Valid") -> Valid
A100: TRX100098 | B100: 45167 | C100: -10569.47 | D100: Expense | E100: Supplies | F100: Retail | G100: East | I100: VEND1065 | J100: Officer Agree Interesting Nice Risk From Medical Some. | K100: Valid | L100: Valid | M100: Valid | N100: =IF(OR(B100="",C100="",D100="",F100=""),"Missing","OK") -> OK | O100: =IF(OR(Table1_17[[#This Row],[amount]]<$Y$8,Table1_17[[#This Row],[amount]]>$Y$7),"Outlier","Normal") -> Normal | P100: =IF(OR(Table1_17[[#This Row],[missing_flag]]="Missing",Table1_17[[#This Row],[outlier_flag]]="Outliers"),"Review","Valid") -> Valid
...
